{
  "8280": {
    "url": "https://www.yelp.com/biz/%C3%B4-comptoir-du-sushi-enghien-les-bains?adjust_creative=NOl6cNLLkrD4j74baZTyew&utm_campaign=yelp_api_v3&utm_medium=api_v3_business_search&utm_source=NOl6cNLLkrD4j74baZTyew",
    "image_url": "https://s3-media2.fl.yelpcdn.com/bphoto/ZR4L6164tNx8d7itJhqUxQ/o.jpg",
    "name": "Ô Comptoir du Sushi",
    "alias": "ô-comptoir-du-sushi-enghien-les-bains",
    "main_category": "Restaurants and Food",
    "sub_categories": "Japanese, ",
    "rating": 4.0,
    "price": null,
    "address": "5 Rue Jean-Monnet",
    "city_from_postal": "Arrondissement de Sarcelles",
    "city": "Enghien-Les-Bains",
    "zip_code": "95880",
    "country_code": "FR",
    "state_code": "95",
    "phone": "+33134171300",
    "review_count": 6,
    "snippets": []
  },
  "13775": {
    "url": "https://www.yelp.com/biz/mcdonalds-garges-l%C3%A8s-gonesse?adjust_creative=NOl6cNLLkrD4j74baZTyew&utm_campaign=yelp_api_v3&utm_medium=api_v3_business_search&utm_source=NOl6cNLLkrD4j74baZTyew",
    "image_url": "https://s3-media3.fl.yelpcdn.com/bphoto/cgzySIq5oFKqSPD0XN1XBQ/o.jpg",
    "name": "McDonald's",
    "alias": "mcdonalds-garges-lès-gonesse",
    "main_category": "Restaurants and Food",
    "sub_categories": "Fast Food, Burgers, ",
    "rating": 4.0,
    "price": "€€",
    "address": "47-51 avenue de Stalingrad",
    "city_from_postal": "Arrondissement de Sarcelles",
    "city": "Garges-lès-Gonesse",
    "zip_code": "95140",
    "country_code": "FR",
    "state_code": "95",
    "phone": "+33139863950",
    "review_count": 2,
    "snippets": []
  },
  "32743": {
    "url": "https://www.yelp.com/biz/le-royal-shah-jahan-enghien-les-bains?adjust_creative=NOl6cNLLkrD4j74baZTyew&utm_campaign=yelp_api_v3&utm_medium=api_v3_business_search&utm_source=NOl6cNLLkrD4j74baZTyew",
    "image_url": "https://s3-media1.fl.yelpcdn.com/bphoto/PIWJfKkG_xBAiVFZZmtfJw/o.jpg",
    "name": "Le Royal Shah Jahan",
    "alias": "le-royal-shah-jahan-enghien-les-bains",
    "main_category": "Restaurants and Food",
    "sub_categories": "Indian, ",
    "rating": 4.5,
    "price": "€€€",
    "address": "70 bis rue du Général de Gaulle",
    "city_from_postal": "Arrondissement de Sarcelles",
    "city": "Enghien-les-Bains",
    "zip_code": "95880",
    "country_code": "FR",
    "state_code": "95",
    "phone": "+33139648888",
    "review_count": 13,
    "snippets": []
  },
  "32878": {
    "url": "https://www.yelp.com/biz/g20-arnouville?adjust_creative=5hutJMpTIMEz7crE-Bac2Q&utm_campaign=yelp_api_v3&utm_medium=api_v3_business_search&utm_source=5hutJMpTIMEz7crE-Bac2Q",
    "image_url": "https://s3-media1.fl.yelpcdn.com/bphoto/n5FEBQsAySZE--p9RfrsbA/o.jpg",
    "name": "G20",
    "alias": "g20-arnouville",
    "main_category": "Restaurants and Food",
    "sub_categories": "Grocery, ",
    "rating": 4.0,
    "price": null,
    "address": "10 bis avenue Pierre Sémard",
    "city_from_postal": "Arrondissement de Sarcelles",
    "city": "Arnouville",
    "zip_code": "95400",
    "country_code": "FR",
    "state_code": "95",
    "phone": "+33139853108",
    "review_count": 1,
    "snippets": []
  },
  "36640": {
    "url": "https://www.yelp.com/biz/qila-restaurant-sarcelles?adjust_creative=5hutJMpTIMEz7crE-Bac2Q&utm_campaign=yelp_api_v3&utm_medium=api_v3_business_search&utm_source=5hutJMpTIMEz7crE-Bac2Q",
    "image_url": "https://s3-media3.fl.yelpcdn.com/bphoto/2CHNCOeCz76_lCgp2jC00A/o.jpg",
    "name": "Qila Restaurant",
    "alias": "qila-restaurant-sarcelles",
    "main_category": "Restaurants and Food",
    "sub_categories": "Indian, French, Pakistani, ",
    "rating": 5.0,
    "price": null,
    "address": "3 bd François Mitterand",
    "city_from_postal": "Arrondissement de Sarcelles",
    "city": "Sarcelles",
    "zip_code": "95200",
    "country_code": "FR",
    "state_code": "95",
    "phone": "+33134070808",
    "review_count": 1,
    "snippets": []
  },
  "37044": {
    "url": "https://www.yelp.com/biz/denis-rennes-soisy-sous-montmorency?adjust_creative=5hutJMpTIMEz7crE-Bac2Q&utm_campaign=yelp_api_v3&utm_medium=api_v3_business_search&utm_source=5hutJMpTIMEz7crE-Bac2Q",
    "image_url": "",
    "name": "Denis Rennes",
    "alias": "denis-rennes-soisy-sous-montmorency",
    "main_category": "Restaurants and Food",
    "sub_categories": "Butcher, ",
    "rating": 5.0,
    "price": "€",
    "address": "11 bis rue Carnot",
    "city_from_postal": "Arrondissement de Sarcelles",
    "city": "Soisy Sous Montmorency",
    "zip_code": "95230",
    "country_code": "FR",
    "state_code": "95",
    "phone": "+33139890380",
    "review_count": 1,
    "snippets": []
  },
  "44846": {
    "url": "https://www.yelp.com/biz/le-paris-enghien-enghien-les-bains?adjust_creative=NOl6cNLLkrD4j74baZTyew&utm_campaign=yelp_api_v3&utm_medium=api_v3_business_search&utm_source=NOl6cNLLkrD4j74baZTyew",
    "image_url": "",
    "name": "Le Paris-Enghien",
    "alias": "le-paris-enghien-enghien-les-bains",
    "main_category": "Restaurants and Food",
    "sub_categories": "Bistros, Brasseries, ",
    "rating": 3.0,
    "price": null,
    "address": "1 Rue de l'Arrivée",
    "city_from_postal": "Arrondissement de Sarcelles",
    "city": "Enghien-Les-Bains",
    "zip_code": "95880",
    "country_code": "FR",
    "state_code": "95",
    "phone": "+33134128028",
    "review_count": 1,
    "snippets": []
  },
  "54983": {
    "url": "https://www.yelp.com/biz/jiu-jitsu-club-d-enghien-enghien-les-bains?adjust_creative=NOl6cNLLkrD4j74baZTyew&utm_campaign=yelp_api_v3&utm_medium=api_v3_business_search&utm_source=NOl6cNLLkrD4j74baZTyew",
    "image_url": "",
    "name": "Jiu Jitsu Club d'Enghien",
    "alias": "jiu-jitsu-club-d-enghien-enghien-les-bains",
    "main_category": "Active Life",
    "sub_categories": "Martial Arts, ",
    "rating": 4.0,
    "price": null,
    "address": "1 bis Rue Le Veillard",
    "city_from_postal": "Arrondissement de Sarcelles",
    "city": "Enghien Les Bains",
    "zip_code": "95880",
    "country_code": "FR",
    "state_code": "95",
    "phone": "+33139896771",
    "review_count": 1,
    "snippets": []
  },
  "65345": {
    "url": "https://www.yelp.com/biz/noujoum-enghien-les-bains?adjust_creative=5hutJMpTIMEz7crE-Bac2Q&utm_campaign=yelp_api_v3&utm_medium=api_v3_business_search&utm_source=5hutJMpTIMEz7crE-Bac2Q",
    "image_url": "https://s3-media1.fl.yelpcdn.com/bphoto/25AYNOC5eHDzXKCtqqTtYQ/o.jpg",
    "name": "Noujoum",
    "alias": "noujoum-enghien-les-bains",
    "main_category": "Restaurants and Food",
    "sub_categories": "Lebanese, ",
    "rating": 3.5,
    "price": null,
    "address": "58 rue du General de Gaulle",
    "city_from_postal": "Arrondissement de Sarcelles",
    "city": "Enghien Les Bains",
    "zip_code": "95880",
    "country_code": "FR",
    "state_code": "95",
    "phone": "+33139594820",
    "review_count": 2,
    "snippets": []
  },
  "74291": {
    "url": "https://www.yelp.com/biz/la-coussay-deuil-la-barre?adjust_creative=NOl6cNLLkrD4j74baZTyew&utm_campaign=yelp_api_v3&utm_medium=api_v3_business_search&utm_source=NOl6cNLLkrD4j74baZTyew",
    "image_url": "",
    "name": "La Coussay",
    "alias": "la-coussay-deuil-la-barre",
    "main_category": "Active Life",
    "sub_categories": "Active Life, Stadiums & Arenas, ",
    "rating": 5.0,
    "price": null,
    "address": "Rue dr schweitzer",
    "city_from_postal": "Arrondissement de Sarcelles",
    "city": "Deuil la Barre",
    "zip_code": "95170",
    "country_code": "FR",
    "state_code": "95",
    "phone": "",
    "review_count": 1,
    "snippets": []
  },
  "75267": {
    "url": "https://www.yelp.com/biz/istambul-2000-sarcelles?adjust_creative=NOl6cNLLkrD4j74baZTyew&utm_campaign=yelp_api_v3&utm_medium=api_v3_business_search&utm_source=NOl6cNLLkrD4j74baZTyew",
    "image_url": "",
    "name": "Istambul 2000",
    "alias": "istambul-2000-sarcelles",
    "main_category": "Restaurants and Food",
    "sub_categories": "Fast Food, ",
    "rating": 5.0,
    "price": null,
    "address": "7 Boulevard Edouard Branly",
    "city_from_postal": "Arrondissement de Sarcelles",
    "city": "Sarcelles",
    "zip_code": "95200",
    "country_code": "FR",
    "state_code": "95",
    "phone": "+33134381232",
    "review_count": 1,
    "snippets": []
  },
  "79577": {
    "url": "https://www.yelp.com/biz/armstrongs-corner-enghien-les-bains?adjust_creative=5hutJMpTIMEz7crE-Bac2Q&utm_campaign=yelp_api_v3&utm_medium=api_v3_business_search&utm_source=5hutJMpTIMEz7crE-Bac2Q",
    "image_url": "https://s3-media1.fl.yelpcdn.com/bphoto/g-z1QBEHX_Gh73Ig6FH1PA/o.jpg",
    "name": "Armstrong's Corner",
    "alias": "armstrongs-corner-enghien-les-bains",
    "main_category": "Restaurants and Food",
    "sub_categories": "Tea Rooms, Desserts, ",
    "rating": 2.0,
    "price": null,
    "address": "3 rue Jean Monnet",
    "city_from_postal": "Arrondissement de Sarcelles",
    "city": "Enghien les Bains",
    "zip_code": "95880",
    "country_code": "FR",
    "state_code": "95",
    "phone": "+33139645501",
    "review_count": 1,
    "snippets": []
  },
  "83465": {
    "url": "https://www.yelp.com/biz/jacques-pr%C3%A9vert-gonesse?adjust_creative=NOl6cNLLkrD4j74baZTyew&utm_campaign=yelp_api_v3&utm_medium=api_v3_business_search&utm_source=NOl6cNLLkrD4j74baZTyew",
    "image_url": "",
    "name": "Jacques Prévert",
    "alias": "jacques-prévert-gonesse",
    "main_category": "Arts & Entertainment",
    "sub_categories": "Cinema, ",
    "rating": 5.0,
    "price": null,
    "address": "Place du Maréchal Lyautey",
    "city_from_postal": "Arrondissement de Sarcelles",
    "city": "Gonesse",
    "zip_code": "95500",
    "country_code": "FR",
    "state_code": "95",
    "phone": "+33139852192",
    "review_count": 1,
    "snippets": []
  },
  "85662": {
    "url": "https://www.yelp.com/biz/h-c-billard-et-chicha-gonesse?adjust_creative=5hutJMpTIMEz7crE-Bac2Q&utm_campaign=yelp_api_v3&utm_medium=api_v3_business_search&utm_source=5hutJMpTIMEz7crE-Bac2Q",
    "image_url": "",
    "name": "H C Billard Et Chicha",
    "alias": "h-c-billard-et-chicha-gonesse",
    "main_category": "Nightlife",
    "sub_categories": "Pool Halls, ",
    "rating": 4.0,
    "price": null,
    "address": "1 Rond Point De Bonneuille",
    "city_from_postal": "Arrondissement de Sarcelles",
    "city": "Gonesse",
    "zip_code": "95500",
    "country_code": "FR",
    "state_code": "95",
    "phone": "",
    "review_count": 1,
    "snippets": []
  },
  "85714": {
    "url": "https://www.yelp.com/biz/le-shine-sarcelles?adjust_creative=5hutJMpTIMEz7crE-Bac2Q&utm_campaign=yelp_api_v3&utm_medium=api_v3_business_search&utm_source=5hutJMpTIMEz7crE-Bac2Q",
    "image_url": "",
    "name": "Le Shine",
    "alias": "le-shine-sarcelles",
    "main_category": "Restaurants and Food",
    "sub_categories": "Sushi Bars, Pan Asian, ",
    "rating": 4.0,
    "price": "€€€",
    "address": "83 avenue Paul Valéry",
    "city_from_postal": "Arrondissement de Sarcelles",
    "city": "Sarcelles",
    "zip_code": "95200",
    "country_code": "FR",
    "state_code": "95",
    "phone": "+33134291717",
    "review_count": 1,
    "snippets": []
  },
  "88411": {
    "url": "https://www.yelp.com/biz/pizza-chic-st-gratien?adjust_creative=5hutJMpTIMEz7crE-Bac2Q&utm_campaign=yelp_api_v3&utm_medium=api_v3_business_search&utm_source=5hutJMpTIMEz7crE-Bac2Q",
    "image_url": "",
    "name": "Pizza Chic",
    "alias": "pizza-chic-st-gratien",
    "main_category": "Restaurants and Food",
    "sub_categories": "Pizza, Italian, ",
    "rating": 4.0,
    "price": null,
    "address": "1 place Gare",
    "city_from_postal": "Arrondissement de Sarcelles",
    "city": "St Gratien",
    "zip_code": "95210",
    "country_code": "FR",
    "state_code": "95",
    "phone": "+33134120109",
    "review_count": 1,
    "snippets": []
  },
  "93061": {
    "url": "https://www.yelp.com/biz/alimentation-g%C3%A9n%C3%A9rale-soisy-sous-montmorency?adjust_creative=5hutJMpTIMEz7crE-Bac2Q&utm_campaign=yelp_api_v3&utm_medium=api_v3_business_search&utm_source=5hutJMpTIMEz7crE-Bac2Q",
    "image_url": "https://s3-media1.fl.yelpcdn.com/bphoto/_piLfrMlQbR_iuwX6RrxZA/o.jpg",
    "name": "Alimentation Générale",
    "alias": "alimentation-générale-soisy-sous-montmorency",
    "main_category": "Restaurants and Food",
    "sub_categories": "Grocery, ",
    "rating": 5.0,
    "price": "€€",
    "address": "1 avenue Descartes",
    "city_from_postal": "Arrondissement de Sarcelles",
    "city": "Soisy-sous-Montmorency",
    "zip_code": "95230",
    "country_code": "FR",
    "state_code": "95",
    "phone": "+33139842413",
    "review_count": 1,
    "snippets": []
  },
  "94963": {
    "url": "https://www.yelp.com/biz/lac-d-enghien-les-bains-enghien-les-bains?adjust_creative=NOl6cNLLkrD4j74baZTyew&utm_campaign=yelp_api_v3&utm_medium=api_v3_business_search&utm_source=NOl6cNLLkrD4j74baZTyew",
    "image_url": "https://s3-media3.fl.yelpcdn.com/bphoto/0mNOk8ZskDIj_QQDzpjQDg/o.jpg",
    "name": "Lac d'Enghien les Bains",
    "alias": "lac-d-enghien-les-bains-enghien-les-bains",
    "main_category": "Active Life",
    "sub_categories": "Lakes, ",
    "rating": 4.0,
    "price": null,
    "address": null,
    "city_from_postal": "Arrondissement de Sarcelles",
    "city": "Enghien les Bains",
    "zip_code": "95880",
    "country_code": "FR",
    "state_code": "95",
    "phone": "",
    "review_count": 11,
    "snippets": []
  },
  "98041": {
    "url": "https://www.yelp.com/biz/au-festin-du-dragon-garges-l%C3%A8s-gonesse-2?adjust_creative=NOl6cNLLkrD4j74baZTyew&utm_campaign=yelp_api_v3&utm_medium=api_v3_business_search&utm_source=NOl6cNLLkrD4j74baZTyew",
    "image_url": "",
    "name": "Au festin du dragon",
    "alias": "au-festin-du-dragon-garges-lès-gonesse-2",
    "main_category": "Restaurants and Food",
    "sub_categories": "Chinese, ",
    "rating": 5.0,
    "price": null,
    "address": "5 Rue Marcel Cerdan",
    "city_from_postal": "Arrondissement de Sarcelles",
    "city": "Garges lès Gonesse",
    "zip_code": "95140",
    "country_code": "FR",
    "state_code": "95",
    "phone": "",
    "review_count": 2,
    "snippets": []
  },
  "99099": {
    "url": "https://www.yelp.com/biz/au-jardin-d-enghien-enghien-les-bains?adjust_creative=5hutJMpTIMEz7crE-Bac2Q&utm_campaign=yelp_api_v3&utm_medium=api_v3_business_search&utm_source=5hutJMpTIMEz7crE-Bac2Q",
    "image_url": "https://s3-media1.fl.yelpcdn.com/bphoto/Qx0zRc8JbB5k4QluZN6ojQ/o.jpg",
    "name": "Au Jardin d'Enghien",
    "alias": "au-jardin-d-enghien-enghien-les-bains",
    "main_category": "Restaurants and Food",
    "sub_categories": "Ice Cream & Frozen Yogurt, ",
    "rating": 5.0,
    "price": null,
    "address": "49 rue du Général de Gaulle",
    "city_from_postal": "Arrondissement de Sarcelles",
    "city": "Enghien les Bains",
    "zip_code": "95880",
    "country_code": "FR",
    "state_code": "95",
    "phone": "+33139648040",
    "review_count": 1,
    "snippets": []
  },
  "106715": {
    "url": "https://www.yelp.com/biz/saveurs-d-asie-st-gratien?adjust_creative=5hutJMpTIMEz7crE-Bac2Q&utm_campaign=yelp_api_v3&utm_medium=api_v3_business_search&utm_source=5hutJMpTIMEz7crE-Bac2Q",
    "image_url": "https://s3-media4.fl.yelpcdn.com/bphoto/bAX0C93B50aO9-KF7a6Q3A/o.jpg",
    "name": "Saveurs d'Asie",
    "alias": "saveurs-d-asie-st-gratien",
    "main_category": "Restaurants and Food",
    "sub_categories": "Chinese, Pan Asian, ",
    "rating": 3.0,
    "price": "€€",
    "address": "22 Rue Berthie Albrecht",
    "city_from_postal": "Arrondissement de Sarcelles",
    "city": "St Gratien",
    "zip_code": "95210",
    "country_code": "FR",
    "state_code": "95",
    "phone": "",
    "review_count": 3,
    "snippets": []
  },
  "107778": {
    "url": "https://www.yelp.com/biz/le-cacaotier-hubert-masse-chocolatier-enghien-les-bains-4?adjust_creative=5hutJMpTIMEz7crE-Bac2Q&utm_campaign=yelp_api_v3&utm_medium=api_v3_business_search&utm_source=5hutJMpTIMEz7crE-Bac2Q",
    "image_url": "https://s3-media2.fl.yelpcdn.com/bphoto/Czk9ZBOmfZISuPLZSizCHw/o.jpg",
    "name": "Le Cacaotier - Hubert Masse Chocolatier",
    "alias": "le-cacaotier-hubert-masse-chocolatier-enghien-les-bains-4",
    "main_category": "Restaurants and Food",
    "sub_categories": "Chocolatiers & Shops, Macarons, ",
    "rating": 4.5,
    "price": "€€",
    "address": "14 rue de Mora",
    "city_from_postal": "Arrondissement de Sarcelles",
    "city": "Enghien Les Bains",
    "zip_code": "95880",
    "country_code": "FR",
    "state_code": "95",
    "phone": "+33139892931",
    "review_count": 6,
    "snippets": []
  },
  "109419": {
    "url": "https://www.yelp.com/biz/th%C3%A9%C3%A2tre-du-casino-enghien-les-bains-3?adjust_creative=NOl6cNLLkrD4j74baZTyew&utm_campaign=yelp_api_v3&utm_medium=api_v3_business_search&utm_source=NOl6cNLLkrD4j74baZTyew",
    "image_url": "https://s3-media2.fl.yelpcdn.com/bphoto/1paub73scHqtsn5nyyUcHQ/o.jpg",
    "name": "Théâtre du Casino",
    "alias": "théâtre-du-casino-enghien-les-bains-3",
    "main_category": "Arts & Entertainment",
    "sub_categories": "Performing Arts, ",
    "rating": 4.5,
    "price": null,
    "address": "3 Avenue Ceinture",
    "city_from_postal": "Arrondissement de Sarcelles",
    "city": "Enghien Les Bains",
    "zip_code": "95880",
    "country_code": "FR",
    "state_code": "95",
    "phone": "+33139341080",
    "review_count": 3,
    "snippets": []
  },
  "109553": {
    "url": "https://www.yelp.com/biz/baber-saint-gratien-2?adjust_creative=NOl6cNLLkrD4j74baZTyew&utm_campaign=yelp_api_v3&utm_medium=api_v3_business_search&utm_source=NOl6cNLLkrD4j74baZTyew",
    "image_url": "",
    "name": "Baber",
    "alias": "baber-saint-gratien-2",
    "main_category": "Restaurants and Food",
    "sub_categories": "Indian, ",
    "rating": 4.0,
    "price": null,
    "address": "71 bd Pasteur",
    "city_from_postal": "Arrondissement de Sarcelles",
    "city": "Saint Gratien",
    "zip_code": "95210",
    "country_code": "FR",
    "state_code": "95",
    "phone": "+33134174916",
    "review_count": 7,
    "snippets": []
  },
  "115891": {
    "url": "https://www.yelp.com/biz/istanbul-kebab-garges-les-gonesses?adjust_creative=NOl6cNLLkrD4j74baZTyew&utm_campaign=yelp_api_v3&utm_medium=api_v3_business_search&utm_source=NOl6cNLLkrD4j74baZTyew",
    "image_url": "",
    "name": "Istanbul Kebab",
    "alias": "istanbul-kebab-garges-les-gonesses",
    "main_category": "Restaurants and Food",
    "sub_categories": "Fast Food, Kebab, ",
    "rating": 2.0,
    "price": null,
    "address": "5 avenue de Stalingrad",
    "city_from_postal": "Arrondissement de Sarcelles",
    "city": "Garges Les Gonesses",
    "zip_code": "95140",
    "country_code": "FR",
    "state_code": "95",
    "phone": "+33139936526",
    "review_count": 1,
    "snippets": []
  },
  "116477": {
    "url": "https://www.yelp.com/biz/basilic-and-tha%C3%AF-a%C3%A9roville-roissy-en-france?adjust_creative=5hutJMpTIMEz7crE-Bac2Q&utm_campaign=yelp_api_v3&utm_medium=api_v3_business_search&utm_source=5hutJMpTIMEz7crE-Bac2Q",
    "image_url": "https://s3-media4.fl.yelpcdn.com/bphoto/_DTPPVPpprhswhBcjo34UA/o.jpg",
    "name": "Basilic and Thaï - Aéroville",
    "alias": "basilic-and-thaï-aéroville-roissy-en-france",
    "main_category": "Restaurants and Food",
    "sub_categories": "Thai, ",
    "rating": 2.5,
    "price": "€€€",
    "address": "Rue des Buissons",
    "city_from_postal": "Arrondissement de Sarcelles",
    "city": "Roissy-En-France",
    "zip_code": "95700",
    "country_code": "FR",
    "state_code": "95",
    "phone": "",
    "review_count": 6,
    "snippets": []
  },
  "117713": {
    "url": "https://www.yelp.com/biz/biocoop-eco-bio-deuil-la-barre?adjust_creative=5hutJMpTIMEz7crE-Bac2Q&utm_campaign=yelp_api_v3&utm_medium=api_v3_business_search&utm_source=5hutJMpTIMEz7crE-Bac2Q",
    "image_url": "",
    "name": "Biocoop - Eco-Bio",
    "alias": "biocoop-eco-bio-deuil-la-barre",
    "main_category": "Restaurants and Food",
    "sub_categories": "Organic Stores, ",
    "rating": 1.0,
    "price": null,
    "address": "140 boulevard de Montmorency",
    "city_from_postal": "Arrondissement de Sarcelles",
    "city": "Deuil-la-Barre",
    "zip_code": "95170",
    "country_code": "FR",
    "state_code": "95",
    "phone": "+33134281727",
    "review_count": 1,
    "snippets": []
  },
  "131529": {
    "url": "https://www.yelp.com/biz/mcdonalds-gonesse-2?adjust_creative=NOl6cNLLkrD4j74baZTyew&utm_campaign=yelp_api_v3&utm_medium=api_v3_business_search&utm_source=NOl6cNLLkrD4j74baZTyew",
    "image_url": "",
    "name": "McDonald's",
    "alias": "mcdonalds-gonesse-2",
    "main_category": "Restaurants and Food",
    "sub_categories": "Fast Food, Burgers, ",
    "rating": 3.0,
    "price": null,
    "address": "Avenue Gabriel Péri",
    "city_from_postal": "Arrondissement de Sarcelles",
    "city": "Gonesse",
    "zip_code": "95500",
    "country_code": "FR",
    "state_code": "95",
    "phone": "+33139853378",
    "review_count": 1,
    "snippets": []
  },
  "147131": {
    "url": "https://www.yelp.com/biz/champ-de-course-enghien-les-bains?adjust_creative=NOl6cNLLkrD4j74baZTyew&utm_campaign=yelp_api_v3&utm_medium=api_v3_business_search&utm_source=NOl6cNLLkrD4j74baZTyew",
    "image_url": "https://s3-media2.fl.yelpcdn.com/bphoto/xhuGmrHCMBPJVv5Aw349zQ/o.jpg",
    "name": "champ de course",
    "alias": "champ-de-course-enghien-les-bains",
    "main_category": "Health & Medical",
    "sub_categories": "Naturopathic/Holistic, Florists, ",
    "rating": 4.5,
    "price": null,
    "address": null,
    "city_from_postal": "Arrondissement de Sarcelles",
    "city": "Enghien les Bains",
    "zip_code": "95880",
    "country_code": "FR",
    "state_code": "95",
    "phone": "",
    "review_count": 2,
    "snippets": []
  },
  "154164": {
    "url": "https://www.yelp.com/biz/parc-urbain-st-gratien?adjust_creative=NOl6cNLLkrD4j74baZTyew&utm_campaign=yelp_api_v3&utm_medium=api_v3_business_search&utm_source=NOl6cNLLkrD4j74baZTyew",
    "image_url": "",
    "name": "Parc Urbain",
    "alias": "parc-urbain-st-gratien",
    "main_category": "Active Life",
    "sub_categories": "Parks, ",
    "rating": 4.5,
    "price": null,
    "address": "Rue Fossiez",
    "city_from_postal": "Arrondissement de Sarcelles",
    "city": "St Gratien",
    "zip_code": "95210",
    "country_code": "FR",
    "state_code": "95",
    "phone": "",
    "review_count": 2,
    "snippets": []
  },
  "168884": {
    "url": "https://www.yelp.com/biz/o-lisboa-drancy?adjust_creative=5hutJMpTIMEz7crE-Bac2Q&utm_campaign=yelp_api_v3&utm_medium=api_v3_business_search&utm_source=5hutJMpTIMEz7crE-Bac2Q",
    "image_url": "",
    "name": "o lisboa",
    "alias": "o-lisboa-drancy",
    "main_category": "Restaurants and Food",
    "sub_categories": "Restaurants, Karaoke, ",
    "rating": 3.5,
    "price": "€€€",
    "address": "90 Avenue jean jaures",
    "city_from_postal": "Arrondissement de Sarcelles",
    "city": "Drancy",
    "zip_code": "95700",
    "country_code": "FR",
    "state_code": "93",
    "phone": "+33148319579",
    "review_count": 3,
    "snippets": []
  },
  "178310": {
    "url": "https://www.yelp.com/biz/dynasty-china-st-gratien?adjust_creative=NOl6cNLLkrD4j74baZTyew&utm_campaign=yelp_api_v3&utm_medium=api_v3_business_search&utm_source=NOl6cNLLkrD4j74baZTyew",
    "image_url": "https://s3-media2.fl.yelpcdn.com/bphoto/QpUoB3vTrGThD624JxhhQw/o.jpg",
    "name": "Dynasty China",
    "alias": "dynasty-china-st-gratien",
    "main_category": "Restaurants and Food",
    "sub_categories": "Chinese, ",
    "rating": 5.0,
    "price": "€€",
    "address": "15 boulevard du Maréchal Foch",
    "city_from_postal": "Arrondissement de Sarcelles",
    "city": "St Gratien",
    "zip_code": "95210",
    "country_code": "FR",
    "state_code": "95",
    "phone": "+33139899604",
    "review_count": 4,
    "snippets": []
  },
  "184446": {
    "url": "https://www.yelp.com/biz/centre-des-arts-d-enghien-les-bains-enghien-les-bains?adjust_creative=NOl6cNLLkrD4j74baZTyew&utm_campaign=yelp_api_v3&utm_medium=api_v3_business_search&utm_source=NOl6cNLLkrD4j74baZTyew",
    "image_url": "https://s3-media1.fl.yelpcdn.com/bphoto/zsyX-R8bi0NBNGY4PmWuIA/o.jpg",
    "name": "Arts Center of Enghien-les-Bains",
    "alias": "centre-des-arts-d-enghien-les-bains-enghien-les-bains",
    "main_category": "Arts & Entertainment",
    "sub_categories": "Cultural Center, Performing Arts, ",
    "rating": 4.0,
    "price": null,
    "address": "16 rue de la Libération",
    "city_from_postal": "Arrondissement de Sarcelles",
    "city": "Enghien-les-Bains",
    "zip_code": "95880",
    "country_code": "FR",
    "state_code": "95",
    "phone": "+33130108559",
    "review_count": 3,
    "snippets": []
  },
  "188096": {
    "url": "https://www.yelp.com/biz/aristote-enghien-les-bains?adjust_creative=5hutJMpTIMEz7crE-Bac2Q&utm_campaign=yelp_api_v3&utm_medium=api_v3_business_search&utm_source=5hutJMpTIMEz7crE-Bac2Q",
    "image_url": "",
    "name": "Aristote",
    "alias": "aristote-enghien-les-bains",
    "main_category": "Nightlife",
    "sub_categories": "Dance Clubs, ",
    "rating": 2.0,
    "price": null,
    "address": "68 Rue Gén de Gaulle",
    "city_from_postal": "Arrondissement de Sarcelles",
    "city": "Enghien les Bains",
    "zip_code": "95880",
    "country_code": "FR",
    "state_code": "95",
    "phone": "+33134126049",
    "review_count": 2,
    "snippets": []
  },
  "191877": {
    "url": "https://www.yelp.com/biz/etablissements-nicolas-st-gratien?adjust_creative=5hutJMpTIMEz7crE-Bac2Q&utm_campaign=yelp_api_v3&utm_medium=api_v3_business_search&utm_source=5hutJMpTIMEz7crE-Bac2Q",
    "image_url": "",
    "name": "Etablissements Nicolas",
    "alias": "etablissements-nicolas-st-gratien",
    "main_category": "Restaurants and Food",
    "sub_categories": "Beer, Wine & Spirits, ",
    "rating": 4.5,
    "price": null,
    "address": "12 Rue Berthie Albrecht",
    "city_from_postal": "Arrondissement de Sarcelles",
    "city": "St Gratien",
    "zip_code": "95210",
    "country_code": "FR",
    "state_code": "95",
    "phone": "+33134121389",
    "review_count": 3,
    "snippets": []
  },
  "191885": {
    "url": "https://www.yelp.com/biz/casino-deuil-la-barre?adjust_creative=5hutJMpTIMEz7crE-Bac2Q&utm_campaign=yelp_api_v3&utm_medium=api_v3_business_search&utm_source=5hutJMpTIMEz7crE-Bac2Q",
    "image_url": "",
    "name": "Casino",
    "alias": "casino-deuil-la-barre",
    "main_category": "Restaurants and Food",
    "sub_categories": "Department Stores, Grocery, ",
    "rating": 3.0,
    "price": "€€",
    "address": "6 Charles de Gaulle",
    "city_from_postal": "Arrondissement de Sarcelles",
    "city": "Deuil la Barre",
    "zip_code": "95170",
    "country_code": "FR",
    "state_code": "95",
    "phone": "",
    "review_count": 5,
    "snippets": []
  },
  "202043": {
    "url": "https://www.yelp.com/biz/pizza-time-garges-l%C3%A8s-gonesse-2?adjust_creative=5hutJMpTIMEz7crE-Bac2Q&utm_campaign=yelp_api_v3&utm_medium=api_v3_business_search&utm_source=5hutJMpTIMEz7crE-Bac2Q",
    "image_url": "",
    "name": "Pizza Time",
    "alias": "pizza-time-garges-lès-gonesse-2",
    "main_category": "Restaurants and Food",
    "sub_categories": "Pizza, ",
    "rating": 4.0,
    "price": null,
    "address": "57 avenue de Stalingrad",
    "city_from_postal": "Arrondissement de Sarcelles",
    "city": "Garges-lès-Gonesse",
    "zip_code": "95140",
    "country_code": "FR",
    "state_code": "95",
    "phone": "+33139860202",
    "review_count": 4,
    "snippets": []
  },
  "215816": {
    "url": "https://www.yelp.com/biz/usdem-enghien-les-bains?adjust_creative=NOl6cNLLkrD4j74baZTyew&utm_campaign=yelp_api_v3&utm_medium=api_v3_business_search&utm_source=NOl6cNLLkrD4j74baZTyew",
    "image_url": "",
    "name": "Usdem",
    "alias": "usdem-enghien-les-bains",
    "main_category": "Active Life",
    "sub_categories": "Recreation Centers, ",
    "rating": 4.0,
    "price": null,
    "address": null,
    "city_from_postal": "Arrondissement de Sarcelles",
    "city": "Enghien les Bains",
    "zip_code": "95880",
    "country_code": "FR",
    "state_code": "95",
    "phone": "",
    "review_count": 1,
    "snippets": []
  },
  "217726": {
    "url": "https://www.yelp.com/biz/palazzo-garges-l%C3%A8s-gonesse?adjust_creative=5hutJMpTIMEz7crE-Bac2Q&utm_campaign=yelp_api_v3&utm_medium=api_v3_business_search&utm_source=5hutJMpTIMEz7crE-Bac2Q",
    "image_url": "",
    "name": "Palazzo",
    "alias": "palazzo-garges-lès-gonesse",
    "main_category": "Restaurants and Food",
    "sub_categories": "Italian, French, Pizza, ",
    "rating": 4.0,
    "price": null,
    "address": "Place de Eugene Delacroix",
    "city_from_postal": "Arrondissement de Sarcelles",
    "city": "Garges-lès-Gonesse",
    "zip_code": "95140",
    "country_code": "FR",
    "state_code": "95",
    "phone": "",
    "review_count": 1,
    "snippets": []
  },
  "225089": {
    "url": "https://www.yelp.com/biz/sushi-kyo-roissy-en-france?adjust_creative=5hutJMpTIMEz7crE-Bac2Q&utm_campaign=yelp_api_v3&utm_medium=api_v3_business_search&utm_source=5hutJMpTIMEz7crE-Bac2Q",
    "image_url": "https://s3-media2.fl.yelpcdn.com/bphoto/tIA0pqYrhLy0Se-1G7ES5A/o.jpg",
    "name": "Sushi Kyo",
    "alias": "sushi-kyo-roissy-en-france",
    "main_category": "Restaurants and Food",
    "sub_categories": "Sushi Bars, Japanese, ",
    "rating": 4.0,
    "price": null,
    "address": "30 rue des Buissons",
    "city_from_postal": "Arrondissement de Sarcelles",
    "city": "Roissy-en-France",
    "zip_code": "95700",
    "country_code": "FR",
    "state_code": "93",
    "phone": "+33174257229",
    "review_count": 1,
    "snippets": []
  },
  "233432": {
    "url": "https://www.yelp.com/biz/energie-forme-enghien-les-bains?adjust_creative=NOl6cNLLkrD4j74baZTyew&utm_campaign=yelp_api_v3&utm_medium=api_v3_business_search&utm_source=NOl6cNLLkrD4j74baZTyew",
    "image_url": "https://s3-media2.fl.yelpcdn.com/bphoto/LSYRVMEgp5MjtaJJbzUvgA/o.jpg",
    "name": "Energie Forme",
    "alias": "energie-forme-enghien-les-bains",
    "main_category": "Active Life",
    "sub_categories": "Gyms, ",
    "rating": 4.0,
    "price": null,
    "address": "41 bis rue de Malleville",
    "city_from_postal": "Arrondissement de Sarcelles",
    "city": "Enghien-les-Bains",
    "zip_code": "95880",
    "country_code": "FR",
    "state_code": "95",
    "phone": "+33139341818",
    "review_count": 2,
    "snippets": []
  },
  "249875": {
    "url": "https://www.yelp.com/biz/l-atelier-tremblay-en-france?adjust_creative=NOl6cNLLkrD4j74baZTyew&utm_campaign=yelp_api_v3&utm_medium=api_v3_business_search&utm_source=NOl6cNLLkrD4j74baZTyew",
    "image_url": "https://s3-media4.fl.yelpcdn.com/bphoto/3FEhuys0mbQ7Zl0EFHp1jw/o.jpg",
    "name": "L'Atelier",
    "alias": "l-atelier-tremblay-en-france",
    "main_category": "Restaurants and Food",
    "sub_categories": "Burgers, Bistros, ",
    "rating": 3.5,
    "price": "€€",
    "address": "Cc Aéroville",
    "city_from_postal": "Arrondissement de Sarcelles",
    "city": "Tremblay-en-France",
    "zip_code": "95700",
    "country_code": "FR",
    "state_code": "93",
    "phone": "+33174257813",
    "review_count": 4,
    "snippets": []
  },
  "254131": {
    "url": "https://www.yelp.com/biz/franprix-deuil-la-barre?adjust_creative=5hutJMpTIMEz7crE-Bac2Q&utm_campaign=yelp_api_v3&utm_medium=api_v3_business_search&utm_source=5hutJMpTIMEz7crE-Bac2Q",
    "image_url": "",
    "name": "Franprix",
    "alias": "franprix-deuil-la-barre",
    "main_category": "Restaurants and Food",
    "sub_categories": "Department Stores, Grocery, ",
    "rating": 4.0,
    "price": null,
    "address": "7 Rue Ormesson",
    "city_from_postal": "Arrondissement de Sarcelles",
    "city": "Deuil la Barre",
    "zip_code": "95170",
    "country_code": "FR",
    "state_code": "95",
    "phone": "+33139834661",
    "review_count": 1,
    "snippets": []
  },
  "255172": {
    "url": "https://www.yelp.com/biz/mcdonalds-sarcelles?adjust_creative=NOl6cNLLkrD4j74baZTyew&utm_campaign=yelp_api_v3&utm_medium=api_v3_business_search&utm_source=NOl6cNLLkrD4j74baZTyew",
    "image_url": "",
    "name": "McDonald's",
    "alias": "mcdonalds-sarcelles",
    "main_category": "Restaurants and Food",
    "sub_categories": "Fast Food, Burgers, ",
    "rating": 1.0,
    "price": null,
    "address": "8 route de Calais",
    "city_from_postal": "Arrondissement de Sarcelles",
    "city": "Sarcelles",
    "zip_code": "95200",
    "country_code": "FR",
    "state_code": "95",
    "phone": "+33139949600",
    "review_count": 1,
    "snippets": []
  },
  "257247": {
    "url": "https://www.yelp.com/biz/casino-barri%C3%A8re-enghien-les-bains-2?adjust_creative=NOl6cNLLkrD4j74baZTyew&utm_campaign=yelp_api_v3&utm_medium=api_v3_business_search&utm_source=NOl6cNLLkrD4j74baZTyew",
    "image_url": "https://s3-media2.fl.yelpcdn.com/bphoto/5k-wsars92D57G27ID_C1g/o.jpg",
    "name": "Casino Barrière",
    "alias": "casino-barrière-enghien-les-bains-2",
    "main_category": "Arts & Entertainment",
    "sub_categories": "Casinos, ",
    "rating": 3.0,
    "price": null,
    "address": "3 avenue de Ceinture",
    "city_from_postal": "Arrondissement de Sarcelles",
    "city": "Enghien-les-Bains",
    "zip_code": "95880",
    "country_code": "FR",
    "state_code": "95",
    "phone": "+33139341317",
    "review_count": 9,
    "snippets": []
  },
  "266474": {
    "url": "https://www.yelp.com/biz/village-le-montmorency?adjust_creative=NOl6cNLLkrD4j74baZTyew&utm_campaign=yelp_api_v3&utm_medium=api_v3_business_search&utm_source=NOl6cNLLkrD4j74baZTyew",
    "image_url": "",
    "name": "Parc De L Hotel De Ville",
    "alias": "village-le-montmorency",
    "main_category": "Restaurants and Food",
    "sub_categories": "Restaurants, Parks, ",
    "rating": 5.0,
    "price": null,
    "address": "2 avenue Foch",
    "city_from_postal": "Arrondissement de Sarcelles",
    "city": "Montmorency",
    "zip_code": "95160",
    "country_code": "FR",
    "state_code": "95",
    "phone": "+33139349835",
    "review_count": 1,
    "snippets": []
  },
  "269771": {
    "url": "https://www.yelp.com/biz/auchan-soisy-sous-montmorency-2?adjust_creative=5hutJMpTIMEz7crE-Bac2Q&utm_campaign=yelp_api_v3&utm_medium=api_v3_business_search&utm_source=5hutJMpTIMEz7crE-Bac2Q",
    "image_url": "https://s3-media4.fl.yelpcdn.com/bphoto/QYiKQzNHX4UL2cikOEy0VA/o.jpg",
    "name": "Auchan",
    "alias": "auchan-soisy-sous-montmorency-2",
    "main_category": "Restaurants and Food",
    "sub_categories": "Grocery, ",
    "rating": 3.5,
    "price": "€€",
    "address": "28 avenue de Paris",
    "city_from_postal": "Arrondissement de Sarcelles",
    "city": "Soisy-sous-Montmorency",
    "zip_code": "95230",
    "country_code": "FR",
    "state_code": "95",
    "phone": "+33139340283",
    "review_count": 2,
    "snippets": []
  },
  "270519": {
    "url": "https://www.yelp.com/biz/alain-bernard-glaces-enghien-l%C3%A8s-bains?adjust_creative=5hutJMpTIMEz7crE-Bac2Q&utm_campaign=yelp_api_v3&utm_medium=api_v3_business_search&utm_source=5hutJMpTIMEz7crE-Bac2Q",
    "image_url": "https://s3-media3.fl.yelpcdn.com/bphoto/mgnzNDwmo2zxu4PjLedSYw/o.jpg",
    "name": "Alain Bernard Glaces",
    "alias": "alain-bernard-glaces-enghien-lès-bains",
    "main_category": "Restaurants and Food",
    "sub_categories": "Ice Cream & Frozen Yogurt, Patisserie/Cake Shop, ",
    "rating": 4.5,
    "price": "€€",
    "address": "49 rue du Général de Gaulle",
    "city_from_postal": "Arrondissement de Sarcelles",
    "city": "Enghien-lès-Bains",
    "zip_code": "95880",
    "country_code": "FR",
    "state_code": "95",
    "phone": "+33139648040",
    "review_count": 12,
    "snippets": []
  },
  "274555": {
    "url": "https://www.yelp.com/biz/la-sandwicherie-de-la-gare-enghien-les-bains?adjust_creative=NOl6cNLLkrD4j74baZTyew&utm_campaign=yelp_api_v3&utm_medium=api_v3_business_search&utm_source=NOl6cNLLkrD4j74baZTyew",
    "image_url": "",
    "name": "La Sandwicherie de la Gare",
    "alias": "la-sandwicherie-de-la-gare-enghien-les-bains",
    "main_category": "Restaurants and Food",
    "sub_categories": "Fast Food, ",
    "rating": 5.0,
    "price": "€",
    "address": "28 rue Départ",
    "city_from_postal": "Arrondissement de Sarcelles",
    "city": "Enghien les Bains",
    "zip_code": "95880",
    "country_code": "FR",
    "state_code": "95",
    "phone": "+33134124111",
    "review_count": 2,
    "snippets": []
  },
  "275439": {
    "url": "https://www.yelp.com/biz/aux-caves-d-enghien-enghien-les-bains?adjust_creative=5hutJMpTIMEz7crE-Bac2Q&utm_campaign=yelp_api_v3&utm_medium=api_v3_business_search&utm_source=5hutJMpTIMEz7crE-Bac2Q",
    "image_url": "https://s3-media1.fl.yelpcdn.com/bphoto/1VsjWMpWtGEWqvBNrvvL5w/o.jpg",
    "name": "Aux Caves d'Enghien",
    "alias": "aux-caves-d-enghien-enghien-les-bains",
    "main_category": "Restaurants and Food",
    "sub_categories": "Beer, Wine & Spirits, ",
    "rating": 5.0,
    "price": null,
    "address": "30 boulevard d'Ormesson",
    "city_from_postal": "Arrondissement de Sarcelles",
    "city": "Enghien les Bains",
    "zip_code": "95880",
    "country_code": "FR",
    "state_code": "95",
    "phone": "+33134175918",
    "review_count": 2,
    "snippets": []
  },
  "276247": {
    "url": "https://www.yelp.com/biz/monoprix-soisy-sous-montmorency?adjust_creative=5hutJMpTIMEz7crE-Bac2Q&utm_campaign=yelp_api_v3&utm_medium=api_v3_business_search&utm_source=5hutJMpTIMEz7crE-Bac2Q",
    "image_url": "",
    "name": "Monoprix",
    "alias": "monoprix-soisy-sous-montmorency",
    "main_category": "Restaurants and Food",
    "sub_categories": "Grocery, ",
    "rating": 3.0,
    "price": null,
    "address": "2 avenue Mirabeau",
    "city_from_postal": "Arrondissement de Sarcelles",
    "city": "Soisy-sous-Montmorency",
    "zip_code": "95230",
    "country_code": "FR",
    "state_code": "95",
    "phone": "+33139893928",
    "review_count": 1,
    "snippets": []
  },
  "276494": {
    "url": "https://www.yelp.com/biz/belle-arte-pizza-villiers-le-bel-villiers-le-bel?adjust_creative=5hutJMpTIMEz7crE-Bac2Q&utm_campaign=yelp_api_v3&utm_medium=api_v3_business_search&utm_source=5hutJMpTIMEz7crE-Bac2Q",
    "image_url": "https://s3-media3.fl.yelpcdn.com/bphoto/-mEqvIKOytd63MDR7yKHqg/o.jpg",
    "name": "Belle Arte Pizza villiers le bel",
    "alias": "belle-arte-pizza-villiers-le-bel-villiers-le-bel",
    "main_category": "Restaurants and Food",
    "sub_categories": "Pizza, ",
    "rating": 4.0,
    "price": null,
    "address": "2 ave des Charmettes",
    "city_from_postal": "Arrondissement de Sarcelles",
    "city": "Villiers le Bel",
    "zip_code": "95400",
    "country_code": "FR",
    "state_code": "95",
    "phone": "+33134078120",
    "review_count": 1,
    "snippets": []
  },
  "281312": {
    "url": "https://www.yelp.com/biz/quick-gonesse?adjust_creative=NOl6cNLLkrD4j74baZTyew&utm_campaign=yelp_api_v3&utm_medium=api_v3_business_search&utm_source=NOl6cNLLkrD4j74baZTyew",
    "image_url": "https://s3-media1.fl.yelpcdn.com/bphoto/WE_PMex3bBPN3tRQfAySgQ/o.jpg",
    "name": "Quick",
    "alias": "quick-gonesse",
    "main_category": "Restaurants and Food",
    "sub_categories": "Fast Food, ",
    "rating": 2.0,
    "price": "€",
    "address": "117 avenue Plaine de France",
    "city_from_postal": "Arrondissement de Sarcelles",
    "city": "Gonesse",
    "zip_code": "95500",
    "country_code": "FR",
    "state_code": "95",
    "phone": "+33148632517",
    "review_count": 2,
    "snippets": []
  },
  "288982": {
    "url": "https://www.yelp.com/biz/natur%C3%A9o-soisy-sous-montmorency-2?adjust_creative=5hutJMpTIMEz7crE-Bac2Q&utm_campaign=yelp_api_v3&utm_medium=api_v3_business_search&utm_source=5hutJMpTIMEz7crE-Bac2Q",
    "image_url": "",
    "name": "NaturéO",
    "alias": "naturéo-soisy-sous-montmorency-2",
    "main_category": "Restaurants and Food",
    "sub_categories": "Organic Stores, ",
    "rating": 4.5,
    "price": "€€",
    "address": "28/30 avenue de Paris",
    "city_from_postal": "Arrondissement de Sarcelles",
    "city": "Soisy-sous-Montmorency",
    "zip_code": "95230",
    "country_code": "FR",
    "state_code": "95",
    "phone": "+33134061001",
    "review_count": 2,
    "snippets": []
  },
  "289523": {
    "url": "https://www.yelp.com/biz/gymnase-de-deuil-deuil-la-barre?adjust_creative=NOl6cNLLkrD4j74baZTyew&utm_campaign=yelp_api_v3&utm_medium=api_v3_business_search&utm_source=NOl6cNLLkrD4j74baZTyew",
    "image_url": "",
    "name": "Gymnase de Deuil",
    "alias": "gymnase-de-deuil-deuil-la-barre",
    "main_category": "Active Life",
    "sub_categories": "Active Life, ",
    "rating": 4.5,
    "price": null,
    "address": "23 rue pelletier",
    "city_from_postal": "Arrondissement de Sarcelles",
    "city": "Deuil la Barre",
    "zip_code": "95170",
    "country_code": "FR",
    "state_code": "95",
    "phone": "",
    "review_count": 3,
    "snippets": []
  },
  "292510": {
    "url": "https://www.yelp.com/biz/mc-donalds-enghien-les-bains-2?adjust_creative=NOl6cNLLkrD4j74baZTyew&utm_campaign=yelp_api_v3&utm_medium=api_v3_business_search&utm_source=NOl6cNLLkrD4j74baZTyew",
    "image_url": "https://s3-media1.fl.yelpcdn.com/bphoto/JOYTNI7kjydeNqxkR9T2bw/o.jpg",
    "name": "Mc Donald's",
    "alias": "mc-donalds-enghien-les-bains-2",
    "main_category": "Restaurants and Food",
    "sub_categories": "Fast Food, ",
    "rating": 2.0,
    "price": "€",
    "address": "42 Rue Gén de Gaulle",
    "city_from_postal": "Arrondissement de Sarcelles",
    "city": "Enghien les Bains",
    "zip_code": "95880",
    "country_code": "FR",
    "state_code": "95",
    "phone": "+33134126036",
    "review_count": 4,
    "snippets": []
  },
  "299961": {
    "url": "https://www.yelp.com/biz/aux-baguettes-d-asie-soisy-sous-montmorency?adjust_creative=5hutJMpTIMEz7crE-Bac2Q&utm_campaign=yelp_api_v3&utm_medium=api_v3_business_search&utm_source=5hutJMpTIMEz7crE-Bac2Q",
    "image_url": "",
    "name": "Aux Baguettes d'Asie",
    "alias": "aux-baguettes-d-asie-soisy-sous-montmorency",
    "main_category": "Restaurants and Food",
    "sub_categories": "Chinese, Japanese, Thai, ",
    "rating": 4.0,
    "price": "€€",
    "address": "42 rue Carnot",
    "city_from_postal": "Arrondissement de Sarcelles",
    "city": "Soisy sous Montmorency",
    "zip_code": "95230",
    "country_code": "FR",
    "state_code": "95",
    "phone": "+33139896913",
    "review_count": 4,
    "snippets": []
  },
  "309785": {
    "url": "https://www.yelp.com/biz/le-golf-gonesse?adjust_creative=NOl6cNLLkrD4j74baZTyew&utm_campaign=yelp_api_v3&utm_medium=api_v3_business_search&utm_source=NOl6cNLLkrD4j74baZTyew",
    "image_url": "",
    "name": "Le Golf",
    "alias": "le-golf-gonesse",
    "main_category": "Active Life",
    "sub_categories": "Golf, French, ",
    "rating": 3.0,
    "price": null,
    "address": "8 Avenue Pierre Salvi",
    "city_from_postal": "Arrondissement de Sarcelles",
    "city": "Gonesse",
    "zip_code": "95500",
    "country_code": "FR",
    "state_code": "95",
    "phone": "+33139874534",
    "review_count": 1,
    "snippets": []
  },
  "313330": {
    "url": "https://www.yelp.com/biz/la-cri%C3%A9e-gonesse?adjust_creative=5hutJMpTIMEz7crE-Bac2Q&utm_campaign=yelp_api_v3&utm_medium=api_v3_business_search&utm_source=5hutJMpTIMEz7crE-Bac2Q",
    "image_url": "https://s3-media4.fl.yelpcdn.com/bphoto/uG4cY54KqTQUHibse9dsQQ/o.jpg",
    "name": "La Criée",
    "alias": "la-criée-gonesse",
    "main_category": "Restaurants and Food",
    "sub_categories": "Seafood, Mediterranean, ",
    "rating": 4.0,
    "price": "€€",
    "address": "Rond point de Bonneuil",
    "city_from_postal": "Arrondissement de Sarcelles",
    "city": "Gonesse",
    "zip_code": "95500",
    "country_code": "FR",
    "state_code": "95",
    "phone": "+33134537700",
    "review_count": 1,
    "snippets": []
  },
  "313804": {
    "url": "https://www.yelp.com/biz/family-pizza-gonesse?adjust_creative=5hutJMpTIMEz7crE-Bac2Q&utm_campaign=yelp_api_v3&utm_medium=api_v3_business_search&utm_source=5hutJMpTIMEz7crE-Bac2Q",
    "image_url": "https://s3-media2.fl.yelpcdn.com/bphoto/E1pASUrQKbamnnNgYNYkpw/o.jpg",
    "name": "Family Pizza",
    "alias": "family-pizza-gonesse",
    "main_category": "Restaurants and Food",
    "sub_categories": "Pizza, Italian, ",
    "rating": 5.0,
    "price": "€",
    "address": "38 Rue Paris",
    "city_from_postal": "Arrondissement de Sarcelles",
    "city": "Gonesse",
    "zip_code": "95500",
    "country_code": "FR",
    "state_code": "95",
    "phone": "+33139857674",
    "review_count": 2,
    "snippets": []
  },
  "320309": {
    "url": "https://www.yelp.com/biz/la-terrasse-montmorency?adjust_creative=NOl6cNLLkrD4j74baZTyew&utm_campaign=yelp_api_v3&utm_medium=api_v3_business_search&utm_source=NOl6cNLLkrD4j74baZTyew",
    "image_url": "https://s3-media3.fl.yelpcdn.com/bphoto/4p02aW6ZS3C8VH2LlB1vmw/o.jpg",
    "name": "La Terrasse",
    "alias": "la-terrasse-montmorency",
    "main_category": "Restaurants and Food",
    "sub_categories": "Creperies, ",
    "rating": 4.5,
    "price": null,
    "address": "7 Avenue Emile",
    "city_from_postal": "Arrondissement de Sarcelles",
    "city": "Montmorency",
    "zip_code": "95160",
    "country_code": "FR",
    "state_code": "95",
    "phone": "+33139644979",
    "review_count": 2,
    "snippets": []
  },
  "320426": {
    "url": "https://www.yelp.com/biz/hoki-sushi-95-gonesse?adjust_creative=5hutJMpTIMEz7crE-Bac2Q&utm_campaign=yelp_api_v3&utm_medium=api_v3_business_search&utm_source=5hutJMpTIMEz7crE-Bac2Q",
    "image_url": "https://s3-media3.fl.yelpcdn.com/bphoto/W21sMYRpgef_bt_G92OVqw/o.jpg",
    "name": "Hoki Sushi 95",
    "alias": "hoki-sushi-95-gonesse",
    "main_category": "Restaurants and Food",
    "sub_categories": "Japanese, Sushi Bars, ",
    "rating": 2.5,
    "price": null,
    "address": "22 rue Belle Etoile",
    "city_from_postal": "Arrondissement de Sarcelles",
    "city": "Gonesse",
    "zip_code": "95500",
    "country_code": "FR",
    "state_code": "95",
    "phone": "+33149380148",
    "review_count": 3,
    "snippets": []
  },
  "330938": {
    "url": "https://www.yelp.com/biz/smed-enghien-les-bains?adjust_creative=NOl6cNLLkrD4j74baZTyew&utm_campaign=yelp_api_v3&utm_medium=api_v3_business_search&utm_source=NOl6cNLLkrD4j74baZTyew",
    "image_url": "",
    "name": "Smed",
    "alias": "smed-enghien-les-bains",
    "main_category": "Active Life",
    "sub_categories": "Active Life, ",
    "rating": 5.0,
    "price": null,
    "address": null,
    "city_from_postal": "Arrondissement de Sarcelles",
    "city": "Enghien les Bains",
    "zip_code": "95880",
    "country_code": "FR",
    "state_code": "95",
    "phone": "",
    "review_count": 1,
    "snippets": []
  },
  "331655": {
    "url": "https://www.yelp.com/biz/le-bellevue-montmorency?adjust_creative=NOl6cNLLkrD4j74baZTyew&utm_campaign=yelp_api_v3&utm_medium=api_v3_business_search&utm_source=NOl6cNLLkrD4j74baZTyew",
    "image_url": "https://s3-media3.fl.yelpcdn.com/bphoto/zpWRhjxmQj_Wjwx4FeIpmQ/o.jpg",
    "name": "Le Bellevue",
    "alias": "le-bellevue-montmorency",
    "main_category": "Restaurants and Food",
    "sub_categories": "Cafes, Wine Bars, ",
    "rating": 4.0,
    "price": "€€",
    "address": "13 place Roger Levanneur",
    "city_from_postal": "Arrondissement de Sarcelles",
    "city": "Montmorency",
    "zip_code": "95160",
    "country_code": "FR",
    "state_code": "95",
    "phone": "+33172534725",
    "review_count": 8,
    "snippets": []
  },
  "331812": {
    "url": "https://www.yelp.com/biz/100-sushi-gonesse?adjust_creative=5hutJMpTIMEz7crE-Bac2Q&utm_campaign=yelp_api_v3&utm_medium=api_v3_business_search&utm_source=5hutJMpTIMEz7crE-Bac2Q",
    "image_url": "https://s3-media2.fl.yelpcdn.com/bphoto/KW4lXIbZ7VGrnoo_kK0cjg/o.jpg",
    "name": "100 Sushi",
    "alias": "100-sushi-gonesse",
    "main_category": "Restaurants and Food",
    "sub_categories": "Sushi Bars, Japanese, ",
    "rating": 3.0,
    "price": null,
    "address": "3 bis rue Raymond Rambert",
    "city_from_postal": "Arrondissement de Sarcelles",
    "city": "Gonesse",
    "zip_code": "95500",
    "country_code": "FR",
    "state_code": "95",
    "phone": "+33139939393",
    "review_count": 1,
    "snippets": []
  },
  "352057": {
    "url": "https://www.yelp.com/biz/ozo-grill-garges-l%C3%A8s-gonesse?adjust_creative=5hutJMpTIMEz7crE-Bac2Q&utm_campaign=yelp_api_v3&utm_medium=api_v3_business_search&utm_source=5hutJMpTIMEz7crE-Bac2Q",
    "image_url": "https://s3-media1.fl.yelpcdn.com/bphoto/6f1TU98zMj9v5ztX1WzXrw/o.jpg",
    "name": "Ozo Grill",
    "alias": "ozo-grill-garges-lès-gonesse",
    "main_category": "Restaurants and Food",
    "sub_categories": "Kebab, Turkish, ",
    "rating": 5.0,
    "price": null,
    "address": "5 rue Louison Bobet",
    "city_from_postal": "Arrondissement de Sarcelles",
    "city": "Garges-lès-Gonesse",
    "zip_code": "95140",
    "country_code": "FR",
    "state_code": "95",
    "phone": "+33753323751",
    "review_count": 1,
    "snippets": []
  },
  "353066": {
    "url": "https://www.yelp.com/biz/planet-sushi-enghien-les-bains?adjust_creative=5hutJMpTIMEz7crE-Bac2Q&utm_campaign=yelp_api_v3&utm_medium=api_v3_business_search&utm_source=5hutJMpTIMEz7crE-Bac2Q",
    "image_url": "",
    "name": "Planet Sushi",
    "alias": "planet-sushi-enghien-les-bains",
    "main_category": "Restaurants and Food",
    "sub_categories": "Japanese, Sushi Bars, ",
    "rating": 3.5,
    "price": "€€€",
    "address": "43 rue du Général de Gaulle",
    "city_from_postal": "Arrondissement de Sarcelles",
    "city": "Enghien Les Bains",
    "zip_code": "95880",
    "country_code": "FR",
    "state_code": "95",
    "phone": "",
    "review_count": 5,
    "snippets": []
  },
  "363571": {
    "url": "https://www.yelp.com/biz/intermarch%C3%A9-montmagny?adjust_creative=5hutJMpTIMEz7crE-Bac2Q&utm_campaign=yelp_api_v3&utm_medium=api_v3_business_search&utm_source=5hutJMpTIMEz7crE-Bac2Q",
    "image_url": "",
    "name": "Intermarché",
    "alias": "intermarché-montmagny",
    "main_category": "Restaurants and Food",
    "sub_categories": "Grocery, ",
    "rating": 4.0,
    "price": "€€",
    "address": "136 rue Jules Ferry",
    "city_from_postal": "Arrondissement de Sarcelles",
    "city": "Montmagny",
    "zip_code": "95360",
    "country_code": "FR",
    "state_code": "95",
    "phone": "+33134286464",
    "review_count": 2,
    "snippets": []
  },
  "366985": {
    "url": "https://www.yelp.com/biz/nicolas-deuil-la-barre-2?adjust_creative=5hutJMpTIMEz7crE-Bac2Q&utm_campaign=yelp_api_v3&utm_medium=api_v3_business_search&utm_source=5hutJMpTIMEz7crE-Bac2Q",
    "image_url": "",
    "name": "Nicolas",
    "alias": "nicolas-deuil-la-barre-2",
    "main_category": "Restaurants and Food",
    "sub_categories": "Beer, Wine & Spirits, ",
    "rating": 3.0,
    "price": null,
    "address": "9 Rue Eglise",
    "city_from_postal": "Arrondissement de Sarcelles",
    "city": "Deuil La Barre",
    "zip_code": "95170",
    "country_code": "FR",
    "state_code": "95",
    "phone": "+33139834480",
    "review_count": 1,
    "snippets": []
  },
  "377530": {
    "url": "https://www.yelp.com/biz/sherwood-parc-viarmes?adjust_creative=NOl6cNLLkrD4j74baZTyew&utm_campaign=yelp_api_v3&utm_medium=api_v3_business_search&utm_source=NOl6cNLLkrD4j74baZTyew",
    "image_url": "https://s3-media2.fl.yelpcdn.com/bphoto/3COc3HfVPQsjp50CIo5EEw/o.jpg",
    "name": "Sherwood Parc",
    "alias": "sherwood-parc-viarmes",
    "main_category": "Active Life",
    "sub_categories": "Bungee Jumping, Laser Tag, Paintball, ",
    "rating": 3.0,
    "price": null,
    "address": "Chemin des Rouliers",
    "city_from_postal": "Arrondissement de Sarcelles",
    "city": "Viarmes",
    "zip_code": "95270",
    "country_code": "FR",
    "state_code": "95",
    "phone": "+33134093644",
    "review_count": 1,
    "snippets": []
  },
  "383888": {
    "url": "https://www.yelp.com/biz/boucherie-normande-et-du-march%C3%A9-enghien-les-bains-3?adjust_creative=5hutJMpTIMEz7crE-Bac2Q&utm_campaign=yelp_api_v3&utm_medium=api_v3_business_search&utm_source=5hutJMpTIMEz7crE-Bac2Q",
    "image_url": "",
    "name": "Boucherie Normande et du Marché",
    "alias": "boucherie-normande-et-du-marché-enghien-les-bains-3",
    "main_category": "Restaurants and Food",
    "sub_categories": "Butcher, ",
    "rating": 5.0,
    "price": null,
    "address": "3 place Verdun",
    "city_from_postal": "Arrondissement de Sarcelles",
    "city": "Enghien Les Bains",
    "zip_code": "95880",
    "country_code": "FR",
    "state_code": "95",
    "phone": "+33139640570",
    "review_count": 1,
    "snippets": []
  },
  "385508": {
    "url": "https://www.yelp.com/biz/ugc-enghien-les-bains?adjust_creative=NOl6cNLLkrD4j74baZTyew&utm_campaign=yelp_api_v3&utm_medium=api_v3_business_search&utm_source=NOl6cNLLkrD4j74baZTyew",
    "image_url": "https://s3-media2.fl.yelpcdn.com/bphoto/YHWAizzIPSA-390qkCPo-Q/o.jpg",
    "name": "UGC",
    "alias": "ugc-enghien-les-bains",
    "main_category": "Arts & Entertainment",
    "sub_categories": "Cinema, ",
    "rating": 3.0,
    "price": null,
    "address": "38 rue du Général de Gaulle",
    "city_from_postal": "Arrondissement de Sarcelles",
    "city": "Enghien les Bains",
    "zip_code": "95880",
    "country_code": "FR",
    "state_code": "95",
    "phone": "+33146372824",
    "review_count": 13,
    "snippets": []
  },
  "408369": {
    "url": "https://www.yelp.com/biz/alain-dommange-deuil-la-barre?adjust_creative=5hutJMpTIMEz7crE-Bac2Q&utm_campaign=yelp_api_v3&utm_medium=api_v3_business_search&utm_source=5hutJMpTIMEz7crE-Bac2Q",
    "image_url": "",
    "name": "Alain Dommange",
    "alias": "alain-dommange-deuil-la-barre",
    "main_category": "Restaurants and Food",
    "sub_categories": "Butcher, ",
    "rating": 4.0,
    "price": null,
    "address": "15 Rue Eglise",
    "city_from_postal": "Arrondissement de Sarcelles",
    "city": "Deuil La Barre",
    "zip_code": "95170",
    "country_code": "FR",
    "state_code": "95",
    "phone": "+33139833314",
    "review_count": 1,
    "snippets": []
  },
  "417309": {
    "url": "https://www.yelp.com/biz/barakemia-enghien-les-bains?adjust_creative=5hutJMpTIMEz7crE-Bac2Q&utm_campaign=yelp_api_v3&utm_medium=api_v3_business_search&utm_source=5hutJMpTIMEz7crE-Bac2Q",
    "image_url": "https://s3-media1.fl.yelpcdn.com/bphoto/ZeRMruMatt6YWE3MFmxD0Q/o.jpg",
    "name": "Barakemia",
    "alias": "barakemia-enghien-les-bains",
    "main_category": "Restaurants and Food",
    "sub_categories": "Tapas Bars, Caterers, Wine Bars, ",
    "rating": 2.0,
    "price": "€€€",
    "address": "13 rue du Général de Gaulle",
    "city_from_postal": "Arrondissement de Sarcelles",
    "city": "Enghien les Bains",
    "zip_code": "95880",
    "country_code": "FR",
    "state_code": "95",
    "phone": "+33139649713",
    "review_count": 1,
    "snippets": []
  },
  "433460": {
    "url": "https://www.yelp.com/biz/la-vague-soisy-sous-montmorency?adjust_creative=NOl6cNLLkrD4j74baZTyew&utm_campaign=yelp_api_v3&utm_medium=api_v3_business_search&utm_source=NOl6cNLLkrD4j74baZTyew",
    "image_url": "https://s3-media4.fl.yelpcdn.com/bphoto/gHGIiRbHYo60EWDT1bAehA/o.jpg",
    "name": "La Vague",
    "alias": "la-vague-soisy-sous-montmorency",
    "main_category": "Restaurants and Food",
    "sub_categories": "Restaurants, Swimming Pools, ",
    "rating": 3.0,
    "price": "€€€",
    "address": "5 Rue Bleury",
    "city_from_postal": "Arrondissement de Sarcelles",
    "city": "Soisy sous Montmorency",
    "zip_code": "95230",
    "country_code": "FR",
    "state_code": "95",
    "phone": "",
    "review_count": 4,
    "snippets": []
  },
  "435488": {
    "url": "https://www.yelp.com/biz/la-cri%C3%A9e-saint-brice-sous-for%C3%AAt?adjust_creative=5hutJMpTIMEz7crE-Bac2Q&utm_campaign=yelp_api_v3&utm_medium=api_v3_business_search&utm_source=5hutJMpTIMEz7crE-Bac2Q",
    "image_url": "https://s3-media4.fl.yelpcdn.com/bphoto/Vl77Hw0T4e-YraTlExh_Cw/o.jpg",
    "name": "la Criée",
    "alias": "la-criée-saint-brice-sous-forêt",
    "main_category": "Restaurants and Food",
    "sub_categories": "Seafood, ",
    "rating": 3.5,
    "price": "€€€",
    "address": "Route Nationale 1",
    "city_from_postal": "Arrondissement de Sarcelles",
    "city": "Saint-Brice-Sous-Forêt",
    "zip_code": "95350",
    "country_code": "FR",
    "state_code": "95",
    "phone": "+33134196565",
    "review_count": 4,
    "snippets": []
  },
  "442530": {
    "url": "https://www.yelp.com/biz/la-bruxelloise-deuil-la-barre?adjust_creative=5hutJMpTIMEz7crE-Bac2Q&utm_campaign=yelp_api_v3&utm_medium=api_v3_business_search&utm_source=5hutJMpTIMEz7crE-Bac2Q",
    "image_url": "https://s3-media1.fl.yelpcdn.com/bphoto/8qJyGAG3Ssm7gJK6F_psAg/o.jpg",
    "name": "La Bruxelloise",
    "alias": "la-bruxelloise-deuil-la-barre",
    "main_category": "Restaurants and Food",
    "sub_categories": "Bakeries, Ice Cream & Frozen Yogurt, ",
    "rating": 2.5,
    "price": null,
    "address": "54 Rue Barre",
    "city_from_postal": "Arrondissement de Sarcelles",
    "city": "Deuil La Barre",
    "zip_code": "95170",
    "country_code": "FR",
    "state_code": "95",
    "phone": "+33139843435",
    "review_count": 3,
    "snippets": []
  },
  "443152": {
    "url": "https://www.yelp.com/biz/franprix-montmorency?adjust_creative=5hutJMpTIMEz7crE-Bac2Q&utm_campaign=yelp_api_v3&utm_medium=api_v3_business_search&utm_source=5hutJMpTIMEz7crE-Bac2Q",
    "image_url": "https://s3-media1.fl.yelpcdn.com/bphoto/MkcSwd_kEjYH_m9BiC-KJw/o.jpg",
    "name": "Franprix",
    "alias": "franprix-montmorency",
    "main_category": "Restaurants and Food",
    "sub_categories": "Grocery, ",
    "rating": 2.0,
    "price": "€€€",
    "address": "6 rue de Pontoise",
    "city_from_postal": "Arrondissement de Sarcelles",
    "city": "Montmorency",
    "zip_code": "95160",
    "country_code": "FR",
    "state_code": "95",
    "phone": "+33134127791",
    "review_count": 1,
    "snippets": []
  },
  "448103": {
    "url": "https://www.yelp.com/biz/la-maison-montmorency?adjust_creative=NOl6cNLLkrD4j74baZTyew&utm_campaign=yelp_api_v3&utm_medium=api_v3_business_search&utm_source=NOl6cNLLkrD4j74baZTyew",
    "image_url": "",
    "name": "La Maison",
    "alias": "la-maison-montmorency",
    "main_category": "Restaurants and Food",
    "sub_categories": "Bistros, ",
    "rating": 4.0,
    "price": null,
    "address": "8 rue Carnot",
    "city_from_postal": "Arrondissement de Sarcelles",
    "city": "Montmorency",
    "zip_code": "95160",
    "country_code": "FR",
    "state_code": "01",
    "phone": "+33139898206",
    "review_count": 1,
    "snippets": []
  },
  "455314": {
    "url": "https://www.yelp.com/biz/sakura-deuil-la-barre?adjust_creative=5hutJMpTIMEz7crE-Bac2Q&utm_campaign=yelp_api_v3&utm_medium=api_v3_business_search&utm_source=5hutJMpTIMEz7crE-Bac2Q",
    "image_url": "",
    "name": "Sakura",
    "alias": "sakura-deuil-la-barre",
    "main_category": "Restaurants and Food",
    "sub_categories": "Japanese, Sushi Bars, ",
    "rating": 5.0,
    "price": "€€",
    "address": "62 bis avenue Division Leclerc",
    "city_from_postal": "Arrondissement de Sarcelles",
    "city": "Deuil La Barre",
    "zip_code": "95170",
    "country_code": "FR",
    "state_code": "95",
    "phone": "+33139649234",
    "review_count": 1,
    "snippets": []
  },
  "459396": {
    "url": "https://www.yelp.com/biz/il-conte-montmorency?adjust_creative=5hutJMpTIMEz7crE-Bac2Q&utm_campaign=yelp_api_v3&utm_medium=api_v3_business_search&utm_source=5hutJMpTIMEz7crE-Bac2Q",
    "image_url": "",
    "name": "Il Conte",
    "alias": "il-conte-montmorency",
    "main_category": "Restaurants and Food",
    "sub_categories": "Pizza, Italian, ",
    "rating": 4.0,
    "price": null,
    "address": "6 Rue Docteur Millet",
    "city_from_postal": "Arrondissement de Sarcelles",
    "city": "Montmorency",
    "zip_code": "95160",
    "country_code": "FR",
    "state_code": "95",
    "phone": "+33139896517",
    "review_count": 3,
    "snippets": []
  },
  "460199": {
    "url": "https://www.yelp.com/biz/big-five-saint-brice-sous-for%C3%AAt?adjust_creative=NOl6cNLLkrD4j74baZTyew&utm_campaign=yelp_api_v3&utm_medium=api_v3_business_search&utm_source=NOl6cNLLkrD4j74baZTyew",
    "image_url": "https://s3-media3.fl.yelpcdn.com/bphoto/PtyS1LlhEkPQpxX9zS7sDQ/o.jpg",
    "name": "Big Five",
    "alias": "big-five-saint-brice-sous-forêt",
    "main_category": "Arts & Entertainment",
    "sub_categories": "Stadiums & Arenas, ",
    "rating": 4.0,
    "price": null,
    "address": "8 sentier de la Chapelle Saint-Nicolas",
    "city_from_postal": "Arrondissement de Sarcelles",
    "city": "Saint-Brice-sous-Forêt",
    "zip_code": "95350",
    "country_code": "FR",
    "state_code": "95",
    "phone": "+33134450000",
    "review_count": 1,
    "snippets": []
  },
  "460291": {
    "url": "https://www.yelp.com/biz/dominos-pizza-saint-gratien?adjust_creative=5hutJMpTIMEz7crE-Bac2Q&utm_campaign=yelp_api_v3&utm_medium=api_v3_business_search&utm_source=5hutJMpTIMEz7crE-Bac2Q",
    "image_url": "https://s3-media4.fl.yelpcdn.com/bphoto/LdjynqQpQxVTszi23sGNnA/o.jpg",
    "name": "Domino's Pizza",
    "alias": "dominos-pizza-saint-gratien",
    "main_category": "Restaurants and Food",
    "sub_categories": "Pizza, ",
    "rating": 2.5,
    "price": null,
    "address": "70 rue Berthie Albrecht",
    "city_from_postal": "Arrondissement de Sarcelles",
    "city": "Saint-Gratien",
    "zip_code": "95210",
    "country_code": "FR",
    "state_code": "95",
    "phone": "+33134129595",
    "review_count": 3,
    "snippets": []
  },
  "464608": {
    "url": "https://www.yelp.com/biz/lookma-saint-gratien?adjust_creative=5hutJMpTIMEz7crE-Bac2Q&utm_campaign=yelp_api_v3&utm_medium=api_v3_business_search&utm_source=5hutJMpTIMEz7crE-Bac2Q",
    "image_url": "",
    "name": "Lookma",
    "alias": "lookma-saint-gratien",
    "main_category": "Restaurants and Food",
    "sub_categories": "Lebanese, ",
    "rating": 4.5,
    "price": null,
    "address": "31 Boulevard Mar Foch",
    "city_from_postal": "Arrondissement de Sarcelles",
    "city": "Saint Gratien",
    "zip_code": "95210",
    "country_code": "FR",
    "state_code": "95",
    "phone": "+33134174739",
    "review_count": 3,
    "snippets": []
  },
  "470513": {
    "url": "https://www.yelp.com/biz/bella-napoli-enghien-les-bains?adjust_creative=NOl6cNLLkrD4j74baZTyew&utm_campaign=yelp_api_v3&utm_medium=api_v3_business_search&utm_source=NOl6cNLLkrD4j74baZTyew",
    "image_url": "https://s3-media1.fl.yelpcdn.com/bphoto/rcd3fTGJjKb9zqpQJGkSzA/o.jpg",
    "name": "Bella Napoli",
    "alias": "bella-napoli-enghien-les-bains",
    "main_category": "Restaurants and Food",
    "sub_categories": "Fast Food, ",
    "rating": 4.0,
    "price": null,
    "address": "7 rue Robert Schuman",
    "city_from_postal": "Arrondissement de Sarcelles",
    "city": "Enghien Les Bains",
    "zip_code": "95880",
    "country_code": "FR",
    "state_code": "95",
    "phone": "+33134122652",
    "review_count": 3,
    "snippets": []
  },
  "478947": {
    "url": "https://www.yelp.com/biz/br%C3%BBlerie-d-enghien-enghien-les-bains-4?adjust_creative=5hutJMpTIMEz7crE-Bac2Q&utm_campaign=yelp_api_v3&utm_medium=api_v3_business_search&utm_source=5hutJMpTIMEz7crE-Bac2Q",
    "image_url": "",
    "name": "Brûlerie d'Enghien",
    "alias": "brûlerie-d-enghien-enghien-les-bains-4",
    "main_category": "Restaurants and Food",
    "sub_categories": "Coffee & Tea, ",
    "rating": 4.0,
    "price": null,
    "address": "15 Bis Rue Gén De Gaulle",
    "city_from_postal": "Arrondissement de Sarcelles",
    "city": "Enghien Les Bains",
    "zip_code": "95880",
    "country_code": "FR",
    "state_code": "95",
    "phone": "+33134128226",
    "review_count": 1,
    "snippets": []
  },
  "480200": {
    "url": "https://www.yelp.com/biz/bowling-du-stadium-st-gratien?adjust_creative=5hutJMpTIMEz7crE-Bac2Q&utm_campaign=yelp_api_v3&utm_medium=api_v3_business_search&utm_source=5hutJMpTIMEz7crE-Bac2Q",
    "image_url": "https://s3-media2.fl.yelpcdn.com/bphoto/zWwdEk8eChdJOYfIA3EmTg/o.jpg",
    "name": "Bowling du Stadium",
    "alias": "bowling-du-stadium-st-gratien",
    "main_category": "Active Life",
    "sub_categories": "Bowling, Pool Halls, ",
    "rating": 2.5,
    "price": "€€€",
    "address": "31 rue Berthie Albrecht",
    "city_from_postal": "Arrondissement de Sarcelles",
    "city": "St Gratien",
    "zip_code": "95210",
    "country_code": "FR",
    "state_code": "95",
    "phone": "+33134285915",
    "review_count": 6,
    "snippets": []
  },
  "488432": {
    "url": "https://www.yelp.com/biz/univers-pizza-soisy-sous-montmorency-2?adjust_creative=5hutJMpTIMEz7crE-Bac2Q&utm_campaign=yelp_api_v3&utm_medium=api_v3_business_search&utm_source=5hutJMpTIMEz7crE-Bac2Q",
    "image_url": "",
    "name": "Univers Pizza",
    "alias": "univers-pizza-soisy-sous-montmorency-2",
    "main_category": "Restaurants and Food",
    "sub_categories": "Italian, Pizza, ",
    "rating": 3.5,
    "price": "€€",
    "address": "1 place Henri Sestre",
    "city_from_postal": "Arrondissement de Sarcelles",
    "city": "Soisy-sous-Montmorency",
    "zip_code": "95230",
    "country_code": "FR",
    "state_code": "95",
    "phone": "+33134170203",
    "review_count": 4,
    "snippets": []
  },
  "494057": {
    "url": "https://www.yelp.com/biz/le-palais-de-mahraja-montmorency?adjust_creative=NOl6cNLLkrD4j74baZTyew&utm_campaign=yelp_api_v3&utm_medium=api_v3_business_search&utm_source=NOl6cNLLkrD4j74baZTyew",
    "image_url": "https://s3-media3.fl.yelpcdn.com/bphoto/3h93XoaVIIL0ocDGGojwqQ/o.jpg",
    "name": "Le Palais de Mahraja",
    "alias": "le-palais-de-mahraja-montmorency",
    "main_category": "Restaurants and Food",
    "sub_categories": "Indian, ",
    "rating": 4.0,
    "price": null,
    "address": "145 ave Charles de Gaulle",
    "city_from_postal": "Arrondissement de Sarcelles",
    "city": "Montmorency",
    "zip_code": "95160",
    "country_code": "FR",
    "state_code": "95",
    "phone": "+33134281414",
    "review_count": 1,
    "snippets": []
  },
  "495500": {
    "url": "https://www.yelp.com/biz/pizza-des-courses-soisy-sous-montmorency?adjust_creative=5hutJMpTIMEz7crE-Bac2Q&utm_campaign=yelp_api_v3&utm_medium=api_v3_business_search&utm_source=5hutJMpTIMEz7crE-Bac2Q",
    "image_url": "",
    "name": "Pizza des Courses",
    "alias": "pizza-des-courses-soisy-sous-montmorency",
    "main_category": "Restaurants and Food",
    "sub_categories": "Pizza, Salad, Tex-Mex, ",
    "rating": 3.0,
    "price": null,
    "address": "1 avenue Descartes",
    "city_from_postal": "Arrondissement de Sarcelles",
    "city": "Soisy-sous-Montmorency",
    "zip_code": "95230",
    "country_code": "FR",
    "state_code": "95",
    "phone": "",
    "review_count": 1,
    "snippets": []
  },
  "496995": {
    "url": "https://www.yelp.com/biz/les-toiles-3-cin%C3%A9mas-st-gratien?adjust_creative=NOl6cNLLkrD4j74baZTyew&utm_campaign=yelp_api_v3&utm_medium=api_v3_business_search&utm_source=NOl6cNLLkrD4j74baZTyew",
    "image_url": "https://s3-media4.fl.yelpcdn.com/bphoto/FVRRcJ4LI7Cfxy7gAhfdlg/o.jpg",
    "name": "Les Toiles 3 Cinémas",
    "alias": "les-toiles-3-cinémas-st-gratien",
    "main_category": "Arts & Entertainment",
    "sub_categories": "Cinema, ",
    "rating": 3.0,
    "price": null,
    "address": "Place François Truffaut",
    "city_from_postal": "Arrondissement de Sarcelles",
    "city": "St Gratien",
    "zip_code": "95210",
    "country_code": "FR",
    "state_code": "95",
    "phone": "+33134282796",
    "review_count": 1,
    "snippets": []
  },
  "499610": {
    "url": "https://www.yelp.com/biz/hippopotamus-roissy-en-france?adjust_creative=5hutJMpTIMEz7crE-Bac2Q&utm_campaign=yelp_api_v3&utm_medium=api_v3_business_search&utm_source=5hutJMpTIMEz7crE-Bac2Q",
    "image_url": "https://s3-media1.fl.yelpcdn.com/bphoto/6BX3ro--9JUWZErx_XAEHw/o.jpg",
    "name": "Hippopotamus",
    "alias": "hippopotamus-roissy-en-france",
    "main_category": "Restaurants and Food",
    "sub_categories": "Steakhouses, ",
    "rating": 2.5,
    "price": null,
    "address": "309 rue de la Belle Etoile",
    "city_from_postal": "Arrondissement de Sarcelles",
    "city": "Roissy-en-France",
    "zip_code": "95700",
    "country_code": "FR",
    "state_code": "95",
    "phone": "+33148631897",
    "review_count": 6,
    "snippets": []
  },
  "501604": {
    "url": "https://www.yelp.com/biz/mcdonalds-roissy-en-france-5?adjust_creative=NOl6cNLLkrD4j74baZTyew&utm_campaign=yelp_api_v3&utm_medium=api_v3_business_search&utm_source=NOl6cNLLkrD4j74baZTyew",
    "image_url": "https://s3-media4.fl.yelpcdn.com/bphoto/-7KCRbMX3iNFqepTXqZX1g/o.jpg",
    "name": "McDonald's",
    "alias": "mcdonalds-roissy-en-france-5",
    "main_category": "Restaurants and Food",
    "sub_categories": "Fast Food, Burgers, ",
    "rating": 2.5,
    "price": null,
    "address": "30 rue des Buissons",
    "city_from_postal": "Arrondissement de Sarcelles",
    "city": "Roissy-en-France",
    "zip_code": "95700",
    "country_code": "FR",
    "state_code": "93",
    "phone": "+33174257432",
    "review_count": 2,
    "snippets": []
  },
  "502447": {
    "url": "https://www.yelp.com/biz/cr%C3%AAperie-saint-gratien-st-gratien?adjust_creative=NOl6cNLLkrD4j74baZTyew&utm_campaign=yelp_api_v3&utm_medium=api_v3_business_search&utm_source=NOl6cNLLkrD4j74baZTyew",
    "image_url": "",
    "name": "Crêperie Saint Gratien",
    "alias": "crêperie-saint-gratien-st-gratien",
    "main_category": "Restaurants and Food",
    "sub_categories": "Creperies, ",
    "rating": 3.0,
    "price": null,
    "address": "2 rue des Halles",
    "city_from_postal": "Arrondissement de Sarcelles",
    "city": "St Gratien",
    "zip_code": "95210",
    "country_code": "FR",
    "state_code": "95",
    "phone": "+33156470860",
    "review_count": 2,
    "snippets": []
  },
  "517849": {
    "url": "https://www.yelp.com/biz/web-avenir-enghien-les-bains?adjust_creative=5hutJMpTIMEz7crE-Bac2Q&utm_campaign=yelp_api_v3&utm_medium=api_v3_business_search&utm_source=5hutJMpTIMEz7crE-Bac2Q",
    "image_url": "",
    "name": "Web Avenir",
    "alias": "web-avenir-enghien-les-bains",
    "main_category": "Restaurants and Food",
    "sub_categories": "Internet Cafes, ",
    "rating": 1.0,
    "price": null,
    "address": "147 Avenue Charles-de-Gaulle",
    "city_from_postal": "Arrondissement de Sarcelles",
    "city": "Enghien-Les-Bains",
    "zip_code": "95880",
    "country_code": "FR",
    "state_code": "95",
    "phone": "+33139892942",
    "review_count": 1,
    "snippets": []
  },
  "519763": {
    "url": "https://www.yelp.com/biz/l-angus-st-gratien?adjust_creative=5hutJMpTIMEz7crE-Bac2Q&utm_campaign=yelp_api_v3&utm_medium=api_v3_business_search&utm_source=5hutJMpTIMEz7crE-Bac2Q",
    "image_url": "",
    "name": "L'Angus",
    "alias": "l-angus-st-gratien",
    "main_category": "Restaurants and Food",
    "sub_categories": "Steakhouses, ",
    "rating": 3.0,
    "price": "€€€",
    "address": "31 bd Foch",
    "city_from_postal": "Arrondissement de Sarcelles",
    "city": "St Gratien",
    "zip_code": "95210",
    "country_code": "FR",
    "state_code": "95",
    "phone": "+33139898989",
    "review_count": 7,
    "snippets": []
  },
  "537263": {
    "url": "https://www.yelp.com/biz/boucherie-yasmine-deuil-la-barre?adjust_creative=5hutJMpTIMEz7crE-Bac2Q&utm_campaign=yelp_api_v3&utm_medium=api_v3_business_search&utm_source=5hutJMpTIMEz7crE-Bac2Q",
    "image_url": "",
    "name": "boucherie Yasmine",
    "alias": "boucherie-yasmine-deuil-la-barre",
    "main_category": "Restaurants and Food",
    "sub_categories": "Butcher, ",
    "rating": 4.5,
    "price": null,
    "address": "39 rue de la gare",
    "city_from_postal": "Arrondissement de Sarcelles",
    "city": "Deuil la Barre",
    "zip_code": "95170",
    "country_code": "FR",
    "state_code": "95",
    "phone": "+33139837943",
    "review_count": 3,
    "snippets": []
  },
  "549384": {
    "url": "https://www.yelp.com/biz/le-sahara-deuil-la-barre?adjust_creative=5hutJMpTIMEz7crE-Bac2Q&utm_campaign=yelp_api_v3&utm_medium=api_v3_business_search&utm_source=5hutJMpTIMEz7crE-Bac2Q",
    "image_url": "",
    "name": "Le Sahara",
    "alias": "le-sahara-deuil-la-barre",
    "main_category": "Restaurants and Food",
    "sub_categories": "Middle Eastern, ",
    "rating": 4.0,
    "price": "€€",
    "address": "21 rue Eglise",
    "city_from_postal": "Arrondissement de Sarcelles",
    "city": "Deuil La Barre",
    "zip_code": "95170",
    "country_code": "FR",
    "state_code": "95",
    "phone": "+33139347170",
    "review_count": 7,
    "snippets": []
  },
  "549806": {
    "url": "https://www.yelp.com/biz/big-ben-pub-roissy-en-france?adjust_creative=NOl6cNLLkrD4j74baZTyew&utm_campaign=yelp_api_v3&utm_medium=api_v3_business_search&utm_source=NOl6cNLLkrD4j74baZTyew",
    "image_url": "https://s3-media1.fl.yelpcdn.com/bphoto/RUFGRHy0UDufKyJ7gT4lEQ/o.jpg",
    "name": "Big Ben Pub",
    "alias": "big-ben-pub-roissy-en-france",
    "main_category": "Restaurants and Food",
    "sub_categories": "French, Burgers, ",
    "rating": 2.5,
    "price": "€€€",
    "address": "Centre commercial Aéroville",
    "city_from_postal": "Arrondissement de Sarcelles",
    "city": "Roissy-en-France",
    "zip_code": "95700",
    "country_code": "FR",
    "state_code": "95",
    "phone": "+33174371313",
    "review_count": 5,
    "snippets": []
  },
  "558154": {
    "url": "https://www.yelp.com/biz/dounia-deuil-la-barre?adjust_creative=5hutJMpTIMEz7crE-Bac2Q&utm_campaign=yelp_api_v3&utm_medium=api_v3_business_search&utm_source=5hutJMpTIMEz7crE-Bac2Q",
    "image_url": "https://s3-media4.fl.yelpcdn.com/bphoto/7AbQYW1bZ4q73yY7LvpJ9g/o.jpg",
    "name": "Dounia",
    "alias": "dounia-deuil-la-barre",
    "main_category": "Restaurants and Food",
    "sub_categories": "Bakeries, ",
    "rating": 4.0,
    "price": "€€",
    "address": "1 Route St Denis",
    "city_from_postal": "Arrondissement de Sarcelles",
    "city": "Deuil la Barre",
    "zip_code": "95170",
    "country_code": "FR",
    "state_code": "95",
    "phone": "+33139849632",
    "review_count": 4,
    "snippets": []
  },
  "559480": {
    "url": "https://www.yelp.com/biz/mcdonalds-st-gratien?adjust_creative=NOl6cNLLkrD4j74baZTyew&utm_campaign=yelp_api_v3&utm_medium=api_v3_business_search&utm_source=NOl6cNLLkrD4j74baZTyew",
    "image_url": "https://s3-media2.fl.yelpcdn.com/bphoto/t9_Mlwd413V6DKpSZJ0gnA/o.jpg",
    "name": "McDonald's",
    "alias": "mcdonalds-st-gratien",
    "main_category": "Restaurants and Food",
    "sub_categories": "Burgers, Fast Food, ",
    "rating": 3.5,
    "price": null,
    "address": "86 bd du Maréchal Foch",
    "city_from_postal": "Arrondissement de Sarcelles",
    "city": "St Gratien",
    "zip_code": "95210",
    "country_code": "FR",
    "state_code": "95",
    "phone": "+33134121687",
    "review_count": 6,
    "snippets": []
  },
  "579381": {
    "url": "https://www.yelp.com/biz/p%C3%A9ch%C3%A9-mignon-deuil-la-barre?adjust_creative=5hutJMpTIMEz7crE-Bac2Q&utm_campaign=yelp_api_v3&utm_medium=api_v3_business_search&utm_source=5hutJMpTIMEz7crE-Bac2Q",
    "image_url": "",
    "name": "Péché Mignon",
    "alias": "péché-mignon-deuil-la-barre",
    "main_category": "Restaurants and Food",
    "sub_categories": "Bakeries, Patisserie/Cake Shop, ",
    "rating": 4.5,
    "price": "€",
    "address": "4 rue du Château",
    "city_from_postal": "Arrondissement de Sarcelles",
    "city": "Deuil La Barre",
    "zip_code": "95170",
    "country_code": "FR",
    "state_code": "95",
    "phone": "+33139831525",
    "review_count": 4,
    "snippets": []
  },
  "587231": {
    "url": "https://www.yelp.com/biz/les-d%C3%A9lices-d-essaouira-montmorency-5?adjust_creative=5hutJMpTIMEz7crE-Bac2Q&utm_campaign=yelp_api_v3&utm_medium=api_v3_business_search&utm_source=5hutJMpTIMEz7crE-Bac2Q",
    "image_url": "",
    "name": "Les Délices d'Essaouira",
    "alias": "les-délices-d-essaouira-montmorency-5",
    "main_category": "Restaurants and Food",
    "sub_categories": "Moroccan, ",
    "rating": 4.0,
    "price": "€€",
    "address": "14 avenue de la Fontaine René",
    "city_from_postal": "Arrondissement de Sarcelles",
    "city": "Montmorency",
    "zip_code": "95160",
    "country_code": "FR",
    "state_code": "95",
    "phone": "+33134287830",
    "review_count": 2,
    "snippets": []
  },
  "587259": {
    "url": "https://www.yelp.com/biz/paysant-leduc-enghien-les-bains?adjust_creative=5hutJMpTIMEz7crE-Bac2Q&utm_campaign=yelp_api_v3&utm_medium=api_v3_business_search&utm_source=5hutJMpTIMEz7crE-Bac2Q",
    "image_url": "",
    "name": "Paysant-Leduc",
    "alias": "paysant-leduc-enghien-les-bains",
    "main_category": "Restaurants and Food",
    "sub_categories": "Chocolatiers & Shops, Patisserie/Cake Shop, Tea Rooms, ",
    "rating": 4.0,
    "price": "€€€",
    "address": "65 rue du Général de Gaulle",
    "city_from_postal": "Arrondissement de Sarcelles",
    "city": "Enghien Les Bains",
    "zip_code": "95880",
    "country_code": "FR",
    "state_code": "95",
    "phone": "+33134126125",
    "review_count": 1,
    "snippets": []
  },
  "589346": {
    "url": "https://www.yelp.com/biz/au-bureau-enghien-les-bains?adjust_creative=NOl6cNLLkrD4j74baZTyew&utm_campaign=yelp_api_v3&utm_medium=api_v3_business_search&utm_source=NOl6cNLLkrD4j74baZTyew",
    "image_url": "https://s3-media2.fl.yelpcdn.com/bphoto/yx_9t6DpEN_H46AB3pwIxA/o.jpg",
    "name": "Au Bureau",
    "alias": "au-bureau-enghien-les-bains",
    "main_category": "Restaurants and Food",
    "sub_categories": "Brasseries, Pubs, ",
    "rating": 3.0,
    "price": "€€",
    "address": "9 rue de l'Arrivée",
    "city_from_postal": "Arrondissement de Sarcelles",
    "city": "Enghien les Bains",
    "zip_code": "95880",
    "country_code": "FR",
    "state_code": "95",
    "phone": "+33134128565",
    "review_count": 25,
    "snippets": []
  },
  "599648": {
    "url": "https://www.yelp.com/biz/courtepaille-st-brice-sous-for%C3%AAt?adjust_creative=5hutJMpTIMEz7crE-Bac2Q&utm_campaign=yelp_api_v3&utm_medium=api_v3_business_search&utm_source=5hutJMpTIMEz7crE-Bac2Q",
    "image_url": "https://s3-media2.fl.yelpcdn.com/bphoto/96wY002O9VEePCpA3N_lGQ/o.jpg",
    "name": "Courtepaille",
    "alias": "courtepaille-st-brice-sous-forêt",
    "main_category": "Restaurants and Food",
    "sub_categories": "Steakhouses, ",
    "rating": 3.5,
    "price": null,
    "address": "Chapelle St Nicolas",
    "city_from_postal": "Arrondissement de Sarcelles",
    "city": "St Brice sous Forêt",
    "zip_code": "95350",
    "country_code": "FR",
    "state_code": "95",
    "phone": "+33139336132",
    "review_count": 3,
    "snippets": []
  },
  "602152": {
    "url": "https://www.yelp.com/biz/memphis-coffee-saint-brice-sous-for%C3%AAt-2?adjust_creative=5hutJMpTIMEz7crE-Bac2Q&utm_campaign=yelp_api_v3&utm_medium=api_v3_business_search&utm_source=5hutJMpTIMEz7crE-Bac2Q",
    "image_url": "https://s3-media1.fl.yelpcdn.com/bphoto/aR9TiOdhFlKmv_Hdjj1IzA/o.jpg",
    "name": "Memphis Coffee",
    "alias": "memphis-coffee-saint-brice-sous-forêt-2",
    "main_category": "Restaurants and Food",
    "sub_categories": "American (Traditional), Diners, ",
    "rating": 3.5,
    "price": null,
    "address": "8 sentier de la Chapelle Saint-Nicholas",
    "city_from_postal": "Arrondissement de Sarcelles",
    "city": "Saint-Brice-sous-Forêt",
    "zip_code": "95350",
    "country_code": "FR",
    "state_code": "95",
    "phone": "+33139920770",
    "review_count": 3,
    "snippets": []
  },
  "620267": {
    "url": "https://www.yelp.com/biz/piscine-intercommunale-montmorency?adjust_creative=NOl6cNLLkrD4j74baZTyew&utm_campaign=yelp_api_v3&utm_medium=api_v3_business_search&utm_source=NOl6cNLLkrD4j74baZTyew",
    "image_url": "https://s3-media4.fl.yelpcdn.com/bphoto/fwv2KWZasRXmLykSzhW6yA/o.jpg",
    "name": "Piscine Intercommunale",
    "alias": "piscine-intercommunale-montmorency",
    "main_category": "Active Life",
    "sub_categories": "Swimming Pools, ",
    "rating": 3.0,
    "price": null,
    "address": "3 rue Henri Dunant",
    "city_from_postal": "Arrondissement de Sarcelles",
    "city": "Montmorency",
    "zip_code": "95160",
    "country_code": "FR",
    "state_code": "95",
    "phone": "+33134129831",
    "review_count": 3,
    "snippets": []
  },
  "624200": {
    "url": "https://www.yelp.com/biz/supermarch%C3%A9-champion-st-gratien?adjust_creative=5hutJMpTIMEz7crE-Bac2Q&utm_campaign=yelp_api_v3&utm_medium=api_v3_business_search&utm_source=5hutJMpTIMEz7crE-Bac2Q",
    "image_url": "",
    "name": "Supermarché Champion",
    "alias": "supermarché-champion-st-gratien",
    "main_category": "Restaurants and Food",
    "sub_categories": "Grocery, ",
    "rating": 5.0,
    "price": null,
    "address": "32 Rue Berthie Albrecht",
    "city_from_postal": "Arrondissement de Sarcelles",
    "city": "St Gratien",
    "zip_code": "95210",
    "country_code": "FR",
    "state_code": "95",
    "phone": "+33139341405",
    "review_count": 1,
    "snippets": []
  },
  "641356": {
    "url": "https://www.yelp.com/biz/waffle-factory-a%C3%A9roville-roissy-en-france-5?adjust_creative=5hutJMpTIMEz7crE-Bac2Q&utm_campaign=yelp_api_v3&utm_medium=api_v3_business_search&utm_source=5hutJMpTIMEz7crE-Bac2Q",
    "image_url": "https://s3-media2.fl.yelpcdn.com/bphoto/NBmQhGegDuLB0Verp4A-Jw/o.jpg",
    "name": "Waffle Factory Aéroville",
    "alias": "waffle-factory-aéroville-roissy-en-france-5",
    "main_category": "Restaurants and Food",
    "sub_categories": "Waffles, Fast Food, ",
    "rating": 3.5,
    "price": null,
    "address": "30 rue des Buissons",
    "city_from_postal": "Arrondissement de Sarcelles",
    "city": "Roissy-en-France",
    "zip_code": "95700",
    "country_code": "FR",
    "state_code": "95",
    "phone": "+33142214663",
    "review_count": 3,
    "snippets": []
  },
  "652310": {
    "url": "https://www.yelp.com/biz/les-cygnes-st-gratien?adjust_creative=NOl6cNLLkrD4j74baZTyew&utm_campaign=yelp_api_v3&utm_medium=api_v3_business_search&utm_source=NOl6cNLLkrD4j74baZTyew",
    "image_url": "https://s3-media3.fl.yelpcdn.com/bphoto/-NKYkOerPUsUIxBWrPlEuA/o.jpg",
    "name": "Les Cygnes",
    "alias": "les-cygnes-st-gratien",
    "main_category": "Restaurants and Food",
    "sub_categories": "Creperies, Italian, ",
    "rating": 3.5,
    "price": "€€",
    "address": "45 bis rue Berthie Albrecht",
    "city_from_postal": "Arrondissement de Sarcelles",
    "city": "St Gratien",
    "zip_code": "95210",
    "country_code": "FR",
    "state_code": "95",
    "phone": "+33134127172",
    "review_count": 3,
    "snippets": []
  },
  "658991": {
    "url": "https://www.yelp.com/biz/san-paolo-enghien-les-bains-2?adjust_creative=5hutJMpTIMEz7crE-Bac2Q&utm_campaign=yelp_api_v3&utm_medium=api_v3_business_search&utm_source=5hutJMpTIMEz7crE-Bac2Q",
    "image_url": "https://s3-media1.fl.yelpcdn.com/bphoto/80G2R86b5bAw5xZ1Rf64Iw/o.jpg",
    "name": "San Paolo",
    "alias": "san-paolo-enghien-les-bains-2",
    "main_category": "Restaurants and Food",
    "sub_categories": "Italian, Pizza, ",
    "rating": 3.0,
    "price": "€€",
    "address": "1 place Card Mercier",
    "city_from_postal": "Arrondissement de Sarcelles",
    "city": "Enghien Les Bains",
    "zip_code": "95880",
    "country_code": "FR",
    "state_code": "95",
    "phone": "+33134125060",
    "review_count": 4,
    "snippets": []
  },
  "660455": {
    "url": "https://www.yelp.com/biz/kfc-st-brice-sous-for%C3%AAt?adjust_creative=NOl6cNLLkrD4j74baZTyew&utm_campaign=yelp_api_v3&utm_medium=api_v3_business_search&utm_source=NOl6cNLLkrD4j74baZTyew",
    "image_url": "",
    "name": "KFC",
    "alias": "kfc-st-brice-sous-forêt",
    "main_category": "Restaurants and Food",
    "sub_categories": "Fast Food, Chicken Shop, ",
    "rating": 2.0,
    "price": null,
    "address": "Chapelle St Nicolas",
    "city_from_postal": "Arrondissement de Sarcelles",
    "city": "St Brice sous Forêt",
    "zip_code": "95350",
    "country_code": "FR",
    "state_code": "95",
    "phone": "+33139920534",
    "review_count": 4,
    "snippets": []
  },
  "674283": {
    "url": "https://www.yelp.com/biz/pret-a-manger-roissy-en-france?adjust_creative=5hutJMpTIMEz7crE-Bac2Q&utm_campaign=yelp_api_v3&utm_medium=api_v3_business_search&utm_source=5hutJMpTIMEz7crE-Bac2Q",
    "image_url": "https://s3-media4.fl.yelpcdn.com/bphoto/fE4RBPW_tFBiIAkG9WKTBw/o.jpg",
    "name": "Pret A Manger",
    "alias": "pret-a-manger-roissy-en-france",
    "main_category": "Restaurants and Food",
    "sub_categories": "Coffee & Tea, Breakfast & Brunch, ",
    "rating": 3.5,
    "price": "€€",
    "address": "30 rue des Buissons",
    "city_from_postal": "Arrondissement de Sarcelles",
    "city": "Roissy-en-France",
    "zip_code": "95700",
    "country_code": "FR",
    "state_code": "93",
    "phone": "+33174257422",
    "review_count": 4,
    "snippets": []
  },
  "681490": {
    "url": "https://www.yelp.com/biz/bab-salam-enghien-les-bains?adjust_creative=5hutJMpTIMEz7crE-Bac2Q&utm_campaign=yelp_api_v3&utm_medium=api_v3_business_search&utm_source=5hutJMpTIMEz7crE-Bac2Q",
    "image_url": "https://s3-media3.fl.yelpcdn.com/bphoto/q5Z02075K_TyjdeUmqIl5g/o.jpg",
    "name": "Bab Salam",
    "alias": "bab-salam-enghien-les-bains",
    "main_category": "Restaurants and Food",
    "sub_categories": "Moroccan, ",
    "rating": 4.5,
    "price": null,
    "address": "5 rue de Mora",
    "city_from_postal": "Arrondissement de Sarcelles",
    "city": "Enghien Les Bains",
    "zip_code": "95880",
    "country_code": "FR",
    "state_code": "95",
    "phone": "+33134123556",
    "review_count": 2,
    "snippets": []
  },
  "697553": {
    "url": "https://www.yelp.com/biz/hano%C3%AF-enghien-les-bains?adjust_creative=5hutJMpTIMEz7crE-Bac2Q&utm_campaign=yelp_api_v3&utm_medium=api_v3_business_search&utm_source=5hutJMpTIMEz7crE-Bac2Q",
    "image_url": "https://s3-media3.fl.yelpcdn.com/bphoto/Z2-iSTEuGF0_knfN6ZPWYQ/o.jpg",
    "name": "Hanoï",
    "alias": "hanoï-enghien-les-bains",
    "main_category": "Restaurants and Food",
    "sub_categories": "Vietnamese, ",
    "rating": 5.0,
    "price": "€€",
    "address": "3 rue de l'Arrivée",
    "city_from_postal": "Arrondissement de Sarcelles",
    "city": "Enghien-les-Bains",
    "zip_code": "95880",
    "country_code": "FR",
    "state_code": "95",
    "phone": "+33139348630",
    "review_count": 1,
    "snippets": []
  }
}