{
  "11": {
    "url": "https://www.yelp.com/biz/v%C3%A1no%C4%8Dn%C3%AD-trhy-na-n%C3%A1m%C4%9Bst%C3%AD-republiky-plze%C5%88?adjust_creative=5hutJMpTIMEz7crE-Bac2Q&utm_campaign=yelp_api_v3&utm_medium=api_v3_business_search&utm_source=5hutJMpTIMEz7crE-Bac2Q",
    "image_url": "",
    "name": "Vánoční trhy na náměstí Republiky",
    "alias": "vánoční-trhy-na-náměstí-republiky-plzeň",
    "main_category": "Arts & Entertainment",
    "sub_categories": "Christmas Markets, ",
    "rating": 5.0,
    "price": null,
    "address": "Náměstí Republiky",
    "city_from_postal": "Plzeň-jih",
    "city": "Plzeň",
    "zip_code": "301 00",
    "country_code": "CZ",
    "state_code": "PL",
    "phone": "",
    "review_count": 1,
    "snippets": []
  },
  "36566": {
    "url": "https://www.yelp.com/biz/depo2015-plze%C5%88?adjust_creative=5hutJMpTIMEz7crE-Bac2Q&utm_campaign=yelp_api_v3&utm_medium=api_v3_business_search&utm_source=5hutJMpTIMEz7crE-Bac2Q",
    "image_url": "https://s3-media1.fl.yelpcdn.com/bphoto/ZQm3Awz-7CvoU4Rtpa0ZsA/o.jpg",
    "name": "Depo2015",
    "alias": "depo2015-plzeň",
    "main_category": "Arts & Entertainment",
    "sub_categories": "Festivals, ",
    "rating": 4.0,
    "price": null,
    "address": "Presslova 11",
    "city_from_postal": "Plzeň-jih",
    "city": "Plzeň",
    "zip_code": "301 00",
    "country_code": "CZ",
    "state_code": "PL",
    "phone": "",
    "review_count": 2,
    "snippets": []
  },
  "40630": {
    "url": "https://www.yelp.com/biz/kamenn%C3%A1-%C4%8Dajovna-plze%C5%88?adjust_creative=5hutJMpTIMEz7crE-Bac2Q&utm_campaign=yelp_api_v3&utm_medium=api_v3_business_search&utm_source=5hutJMpTIMEz7crE-Bac2Q",
    "image_url": "https://s3-media3.fl.yelpcdn.com/bphoto/yGiN4Ng0zh8s04gMO6945g/o.jpg",
    "name": "Kamenná čajovna",
    "alias": "kamenná-čajovna-plzeň",
    "main_category": "Nightlife",
    "sub_categories": "Hookah Bars, Social Clubs, Tea Rooms, ",
    "rating": 4.0,
    "price": null,
    "address": "Kopeckého sady 152/15",
    "city_from_postal": "Plzeň-jih",
    "city": "Plzeň",
    "zip_code": "301 00",
    "country_code": "CZ",
    "state_code": "PL",
    "phone": "",
    "review_count": 1,
    "snippets": []
  },
  "61356": {
    "url": "https://www.yelp.com/biz/the-pub-plze%C5%88-plze%C5%88-vnit%C5%99n%C3%AD-m%C4%9Bsto?adjust_creative=5hutJMpTIMEz7crE-Bac2Q&utm_campaign=yelp_api_v3&utm_medium=api_v3_business_search&utm_source=5hutJMpTIMEz7crE-Bac2Q",
    "image_url": "https://s3-media2.fl.yelpcdn.com/bphoto/wdkklQuGl1Z6qmV_wimvJQ/o.jpg",
    "name": "The PUB Plzeň",
    "alias": "the-pub-plzeň-plzeň-vnitřní-město",
    "main_category": "Nightlife",
    "sub_categories": "Pubs, Burgers, Czech, ",
    "rating": 4.0,
    "price": "$$",
    "address": "Pražská 1",
    "city_from_postal": "Plzeň-jih",
    "city": "Plzeň-vnitřní město",
    "zip_code": "301 00",
    "country_code": "CZ",
    "state_code": "PL",
    "phone": "+420377321001",
    "review_count": 8,
    "snippets": []
  },
  "114372": {
    "url": "https://www.yelp.com/biz/jekyll-a-hyde-plzen-2?adjust_creative=5hutJMpTIMEz7crE-Bac2Q&utm_campaign=yelp_api_v3&utm_medium=api_v3_business_search&utm_source=5hutJMpTIMEz7crE-Bac2Q",
    "image_url": "https://s3-media1.fl.yelpcdn.com/bphoto/jQ7_ycz8DGmnwWI7ceChYw/o.jpg",
    "name": "Jekyll & Hyde",
    "alias": "jekyll-a-hyde-plzen-2",
    "main_category": "Nightlife",
    "sub_categories": "Dance Clubs, ",
    "rating": 4.0,
    "price": null,
    "address": "Klatovská tř. 818/11",
    "city_from_postal": "Plzeň-jih",
    "city": "Plzen",
    "zip_code": "301 00",
    "country_code": "CZ",
    "state_code": "PL",
    "phone": "+420604631652",
    "review_count": 1,
    "snippets": []
  },
  "140198": {
    "url": "https://www.yelp.com/biz/and%C4%9Bl-caf%C3%A9-a-bar-plzen?adjust_creative=5hutJMpTIMEz7crE-Bac2Q&utm_campaign=yelp_api_v3&utm_medium=api_v3_business_search&utm_source=5hutJMpTIMEz7crE-Bac2Q",
    "image_url": "https://s3-media1.fl.yelpcdn.com/bphoto/PFHHzw42bdl_p2z6zBwbkA/o.jpg",
    "name": "Anděl Café & Bar",
    "alias": "anděl-café-a-bar-plzen",
    "main_category": "Restaurants and Food",
    "sub_categories": "Coffee & Tea, Bars, ",
    "rating": 5.0,
    "price": "$$",
    "address": "Bezručova 5",
    "city_from_postal": "Plzeň-jih",
    "city": "Plzen",
    "zip_code": "301 00",
    "country_code": "CZ",
    "state_code": "PL",
    "phone": "",
    "review_count": 1,
    "snippets": []
  },
  "163004": {
    "url": "https://www.yelp.com/biz/techmania-science-center-plze%C5%88?adjust_creative=5hutJMpTIMEz7crE-Bac2Q&utm_campaign=yelp_api_v3&utm_medium=api_v3_business_search&utm_source=5hutJMpTIMEz7crE-Bac2Q",
    "image_url": "https://s3-media2.fl.yelpcdn.com/bphoto/_bRqT8mZ39RE1ZZVWF4oxg/o.jpg",
    "name": "Techmania Science Center",
    "alias": "techmania-science-center-plzeň",
    "main_category": "Arts & Entertainment",
    "sub_categories": "Children's Museums, Recreation Centers, ",
    "rating": 4.5,
    "price": null,
    "address": "Tylova 2929/59",
    "city_from_postal": "Plzeň-jih",
    "city": "Plzeň",
    "zip_code": "301 00",
    "country_code": "CZ",
    "state_code": "PL",
    "phone": "+420737247586",
    "review_count": 4,
    "snippets": []
  },
  "168460": {
    "url": "https://www.yelp.com/biz/pivovarsk%C3%A9-muzeum-plzen?adjust_creative=5hutJMpTIMEz7crE-Bac2Q&utm_campaign=yelp_api_v3&utm_medium=api_v3_business_search&utm_source=5hutJMpTIMEz7crE-Bac2Q",
    "image_url": "https://s3-media1.fl.yelpcdn.com/bphoto/mfRJQUWt1niqgjdetrJdzg/o.jpg",
    "name": "Pivovarské muzeum",
    "alias": "pivovarské-muzeum-plzen",
    "main_category": "Arts & Entertainment",
    "sub_categories": "Museums, ",
    "rating": 4.0,
    "price": null,
    "address": "Veleslavínova 58/6",
    "city_from_postal": "Plzeň-jih",
    "city": "Plzen",
    "zip_code": "301 00",
    "country_code": "CZ",
    "state_code": "PL",
    "phone": "+420377235574",
    "review_count": 1,
    "snippets": []
  },
  "192939": {
    "url": "https://www.yelp.com/biz/vin%C3%A1rna-hrozen-plzen?adjust_creative=5hutJMpTIMEz7crE-Bac2Q&utm_campaign=yelp_api_v3&utm_medium=api_v3_business_search&utm_source=5hutJMpTIMEz7crE-Bac2Q",
    "image_url": "",
    "name": "Vinárna Hrozen",
    "alias": "vinárna-hrozen-plzen",
    "main_category": "Nightlife",
    "sub_categories": "Wine Bars, ",
    "rating": 5.0,
    "price": "$$",
    "address": "Palackého třída 8",
    "city_from_postal": "Plzeň-jih",
    "city": "Plzen",
    "zip_code": "301 00",
    "country_code": "CZ",
    "state_code": "PL",
    "phone": "+420773971250",
    "review_count": 1,
    "snippets": []
  },
  "199688": {
    "url": "https://www.yelp.com/biz/plze%C5%88sk%C3%A9-historick%C3%A9-podzem%C3%AD-plzen?adjust_creative=5hutJMpTIMEz7crE-Bac2Q&utm_campaign=yelp_api_v3&utm_medium=api_v3_business_search&utm_source=5hutJMpTIMEz7crE-Bac2Q",
    "image_url": "",
    "name": "Plzeňské historické podzemí",
    "alias": "plzeňské-historické-podzemí-plzen",
    "main_category": "Arts & Entertainment",
    "sub_categories": "Museums, ",
    "rating": 4.5,
    "price": null,
    "address": "Veleslavinova 58/6",
    "city_from_postal": "Plzeň-jih",
    "city": "Plzen",
    "zip_code": "301 00",
    "country_code": "CZ",
    "state_code": "PL",
    "phone": "+420377235574",
    "review_count": 2,
    "snippets": []
  },
  "202267": {
    "url": "https://www.yelp.com/biz/comix-excelent-urban-pub-plze%C5%88?adjust_creative=5hutJMpTIMEz7crE-Bac2Q&utm_campaign=yelp_api_v3&utm_medium=api_v3_business_search&utm_source=5hutJMpTIMEz7crE-Bac2Q",
    "image_url": "https://s3-media4.fl.yelpcdn.com/bphoto/KZCbxMb1GweiurRT3VF74g/o.jpg",
    "name": "Comix Excelent Urban Pub",
    "alias": "comix-excelent-urban-pub-plzeň",
    "main_category": "Restaurants and Food",
    "sub_categories": "Barbeque, Pubs, Czech, ",
    "rating": 4.5,
    "price": "$$",
    "address": "Náměstí republiky 14a",
    "city_from_postal": "Plzeň-jih",
    "city": "Plzeň",
    "zip_code": "301 00",
    "country_code": "CZ",
    "state_code": "PL",
    "phone": "+420777662800",
    "review_count": 8,
    "snippets": []
  },
  "240946": {
    "url": "https://www.yelp.com/biz/restaurace-galerie-artamo-plze%C5%88-3?adjust_creative=5hutJMpTIMEz7crE-Bac2Q&utm_campaign=yelp_api_v3&utm_medium=api_v3_business_search&utm_source=5hutJMpTIMEz7crE-Bac2Q",
    "image_url": "https://s3-media3.fl.yelpcdn.com/bphoto/x3Cl1Qb1ZZu3sNWL8O0u5A/o.jpg",
    "name": "Restaurace - Galerie - Artamo",
    "alias": "restaurace-galerie-artamo-plzeň-3",
    "main_category": "Arts & Entertainment",
    "sub_categories": "Art Galleries, Barbeque, Italian, ",
    "rating": 3.0,
    "price": null,
    "address": "Čelakovského 5",
    "city_from_postal": "Plzeň-jih",
    "city": "Plzeň 3",
    "zip_code": "301 00",
    "country_code": "CZ",
    "state_code": "PL",
    "phone": "+420605292099",
    "review_count": 1,
    "snippets": []
  },
  "244711": {
    "url": "https://www.yelp.com/biz/zelenohorsk%C3%A1-po%C5%A1ta-expozice-veter%C3%A1n%C5%AF-nepomuk?adjust_creative=5hutJMpTIMEz7crE-Bac2Q&utm_campaign=yelp_api_v3&utm_medium=api_v3_business_search&utm_source=5hutJMpTIMEz7crE-Bac2Q",
    "image_url": "",
    "name": "Zelenohorská pošta - Expozice veteránů",
    "alias": "zelenohorská-pošta-expozice-veteránů-nepomuk",
    "main_category": "Automotive",
    "sub_categories": "Automotive, Art Galleries, Museums, ",
    "rating": 4.0,
    "price": "$",
    "address": "Zelenohorská 76",
    "city_from_postal": "Plzeň-jih",
    "city": "Nepomuk",
    "zip_code": "335 01",
    "country_code": "CZ",
    "state_code": "PL",
    "phone": "+420731015547",
    "review_count": 1,
    "snippets": []
  },
  "318504": {
    "url": "https://www.yelp.com/biz/werk-a-ik-czech-plze%C5%88?adjust_creative=5hutJMpTIMEz7crE-Bac2Q&utm_campaign=yelp_api_v3&utm_medium=api_v3_business_search&utm_source=5hutJMpTIMEz7crE-Bac2Q",
    "image_url": "",
    "name": "Werk & IK czech",
    "alias": "werk-a-ik-czech-plzeň",
    "main_category": "Professional Services",
    "sub_categories": "Employment Agencies, Performing Arts, Wholesale Stores, Advertising, ",
    "rating": 1.0,
    "price": null,
    "address": "Jungmannova 174/7",
    "city_from_postal": "Plzeň-jih",
    "city": "Plzeň",
    "zip_code": "301 00",
    "country_code": "CZ",
    "state_code": "PL",
    "phone": "+420377970277",
    "review_count": 1,
    "snippets": []
  },
  "350164": {
    "url": "https://www.yelp.com/biz/bohemia-sekt-centrum-star%C3%BD-plzenec?adjust_creative=5hutJMpTIMEz7crE-Bac2Q&utm_campaign=yelp_api_v3&utm_medium=api_v3_business_search&utm_source=5hutJMpTIMEz7crE-Bac2Q",
    "image_url": "",
    "name": "Bohemia Sekt Centrum",
    "alias": "bohemia-sekt-centrum-starý-plzenec",
    "main_category": "Arts & Entertainment",
    "sub_categories": "Wineries, ",
    "rating": 5.0,
    "price": null,
    "address": "Smetanova 220",
    "city_from_postal": "Plzeň-jih",
    "city": "Starý Plzenec",
    "zip_code": "332 02",
    "country_code": "CZ",
    "state_code": "PL",
    "phone": "+420377197111",
    "review_count": 1,
    "snippets": []
  },
  "352193": {
    "url": "https://www.yelp.com/biz/o%C5%99echovka-plze%C5%88?adjust_creative=5hutJMpTIMEz7crE-Bac2Q&utm_campaign=yelp_api_v3&utm_medium=api_v3_business_search&utm_source=5hutJMpTIMEz7crE-Bac2Q",
    "image_url": "https://s3-media4.fl.yelpcdn.com/bphoto/HVZh3EBIPbqVNJIxOUcIIw/o.jpg",
    "name": "Ořechovka",
    "alias": "ořechovka-plzeň",
    "main_category": "Restaurants and Food",
    "sub_categories": "Czech, Wineries, ",
    "rating": 3.0,
    "price": null,
    "address": "Ořechová 11",
    "city_from_postal": "Plzeň-jih",
    "city": "Plzeň",
    "zip_code": "326 00",
    "country_code": "CZ",
    "state_code": "PL",
    "phone": "+420377457498",
    "review_count": 1,
    "snippets": []
  },
  "354422": {
    "url": "https://www.yelp.com/biz/beer-factory-plze%C5%88?adjust_creative=5hutJMpTIMEz7crE-Bac2Q&utm_campaign=yelp_api_v3&utm_medium=api_v3_business_search&utm_source=5hutJMpTIMEz7crE-Bac2Q",
    "image_url": "https://s3-media3.fl.yelpcdn.com/bphoto/bRWEW-phZPJSqi3L7CS1fg/o.jpg",
    "name": "Beer Factory",
    "alias": "beer-factory-plzeň",
    "main_category": "Nightlife",
    "sub_categories": "Beer Bar, Pubs, Czech, ",
    "rating": 4.5,
    "price": null,
    "address": "Dominikánská 8",
    "city_from_postal": "Plzeň-jih",
    "city": "Plzeň",
    "zip_code": "301 00",
    "country_code": "CZ",
    "state_code": "PL",
    "phone": "+420379422526",
    "review_count": 4,
    "snippets": []
  },
  "360684": {
    "url": "https://www.yelp.com/biz/%C5%A1achmat-plze%C5%88?adjust_creative=5hutJMpTIMEz7crE-Bac2Q&utm_campaign=yelp_api_v3&utm_medium=api_v3_business_search&utm_source=5hutJMpTIMEz7crE-Bac2Q",
    "image_url": "https://s3-media3.fl.yelpcdn.com/bphoto/9RIoYfoMCj8lIFOUA42Nlg/o.jpg",
    "name": "ŠachMat",
    "alias": "šachmat-plzeň",
    "main_category": "Nightlife",
    "sub_categories": "Pubs, Czech, ",
    "rating": 4.0,
    "price": "$$",
    "address": "Purkyňova 994/29",
    "city_from_postal": "Plzeň-jih",
    "city": "Plzeň",
    "zip_code": "301 00",
    "country_code": "CZ",
    "state_code": "PL",
    "phone": "+420605943499",
    "review_count": 1,
    "snippets": []
  },
  "364287": {
    "url": "https://www.yelp.com/biz/hosp%C5%AFdka-v-bendovce-plze%C5%88?adjust_creative=5hutJMpTIMEz7crE-Bac2Q&utm_campaign=yelp_api_v3&utm_medium=api_v3_business_search&utm_source=5hutJMpTIMEz7crE-Bac2Q",
    "image_url": "https://s3-media3.fl.yelpcdn.com/bphoto/7IfmB1-2jO0CXsreh6fU3Q/o.jpg",
    "name": "Hospůdka v Bendovce",
    "alias": "hospůdka-v-bendovce-plzeň",
    "main_category": "Restaurants and Food",
    "sub_categories": "Brasseries, Pubs, ",
    "rating": 4.0,
    "price": null,
    "address": "Bendova 1548/39",
    "city_from_postal": "Plzeň-jih",
    "city": "Plzeň",
    "zip_code": "301 00",
    "country_code": "CZ",
    "state_code": "PL",
    "phone": "+420774448535",
    "review_count": 1,
    "snippets": []
  },
  "424860": {
    "url": "https://www.yelp.com/biz/jameson-rock-club-plzen?adjust_creative=5hutJMpTIMEz7crE-Bac2Q&utm_campaign=yelp_api_v3&utm_medium=api_v3_business_search&utm_source=5hutJMpTIMEz7crE-Bac2Q",
    "image_url": "https://s3-media1.fl.yelpcdn.com/bphoto/5TcaGr5Jlr1d7gvtQ3w7cw/o.jpg",
    "name": "Jameson Rock Club",
    "alias": "jameson-rock-club-plzen",
    "main_category": "Nightlife",
    "sub_categories": "Bars, ",
    "rating": 3.5,
    "price": "$$",
    "address": "Americká 8",
    "city_from_postal": "Plzeň-jih",
    "city": "Plzen",
    "zip_code": "301 00",
    "country_code": "CZ",
    "state_code": "PL",
    "phone": "+420773675517",
    "review_count": 3,
    "snippets": []
  },
  "425417": {
    "url": "https://www.yelp.com/biz/muzeum-stra%C5%A1idel-plze%C5%88?adjust_creative=5hutJMpTIMEz7crE-Bac2Q&utm_campaign=yelp_api_v3&utm_medium=api_v3_business_search&utm_source=5hutJMpTIMEz7crE-Bac2Q",
    "image_url": "https://s3-media1.fl.yelpcdn.com/bphoto/-ji5BoKP1AFOxCy7rnc9Kg/o.jpg",
    "name": "Muzeum Strašidel",
    "alias": "muzeum-strašidel-plzeň",
    "main_category": "Arts & Entertainment",
    "sub_categories": "Museums, ",
    "rating": 3.0,
    "price": null,
    "address": "Námêstí Republiky 4/3",
    "city_from_postal": "Plzeň-jih",
    "city": "Plzeň",
    "zip_code": "301 00",
    "country_code": "CZ",
    "state_code": "PL",
    "phone": "",
    "review_count": 1,
    "snippets": []
  },
  "427099": {
    "url": "https://www.yelp.com/biz/funky-monkey-plzen?adjust_creative=5hutJMpTIMEz7crE-Bac2Q&utm_campaign=yelp_api_v3&utm_medium=api_v3_business_search&utm_source=5hutJMpTIMEz7crE-Bac2Q",
    "image_url": "https://s3-media4.fl.yelpcdn.com/bphoto/bbA6OLhjRa30nflcfZbe7w/o.jpg",
    "name": "Funky monkey",
    "alias": "funky-monkey-plzen",
    "main_category": "Nightlife",
    "sub_categories": "Pubs, ",
    "rating": 4.0,
    "price": null,
    "address": "Dřevěná 103/6",
    "city_from_postal": "Plzeň-jih",
    "city": "Plzen",
    "zip_code": "301 00",
    "country_code": "CZ",
    "state_code": "PL",
    "phone": "",
    "review_count": 1,
    "snippets": []
  },
  "428662": {
    "url": "https://www.yelp.com/biz/dominik-jazz-rock-caf%C3%A9-plzen?adjust_creative=5hutJMpTIMEz7crE-Bac2Q&utm_campaign=yelp_api_v3&utm_medium=api_v3_business_search&utm_source=5hutJMpTIMEz7crE-Bac2Q",
    "image_url": "https://s3-media2.fl.yelpcdn.com/bphoto/uNcc1OKagKf3axhpL1Lt_g/o.jpg",
    "name": "Dominik Jazz rock café",
    "alias": "dominik-jazz-rock-café-plzen",
    "main_category": "Nightlife",
    "sub_categories": "Bars, ",
    "rating": 3.5,
    "price": "$",
    "address": "Dominikánská 3",
    "city_from_postal": "Plzeň-jih",
    "city": "Plzen",
    "zip_code": "301 00",
    "country_code": "CZ",
    "state_code": "PL",
    "phone": "",
    "review_count": 2,
    "snippets": []
  },
  "438077": {
    "url": "https://www.yelp.com/biz/l%C3%A9k%C3%A1rna-plze%C5%88-4?adjust_creative=5hutJMpTIMEz7crE-Bac2Q&utm_campaign=yelp_api_v3&utm_medium=api_v3_business_search&utm_source=5hutJMpTIMEz7crE-Bac2Q",
    "image_url": "https://s3-media3.fl.yelpcdn.com/bphoto/Gbe0rWCcelSasywI3unbKw/o.jpg",
    "name": "Lékárna",
    "alias": "lékárna-plzeň-4",
    "main_category": "Nightlife",
    "sub_categories": "Pubs, Czech, Modern European, ",
    "rating": 5.0,
    "price": null,
    "address": "Nám. Republiky 97/9",
    "city_from_postal": "Plzeň-jih",
    "city": "Plzeň",
    "zip_code": "301 00",
    "country_code": "CZ",
    "state_code": "PL",
    "phone": "+420735123648",
    "review_count": 1,
    "snippets": []
  },
  "453930": {
    "url": "https://www.yelp.com/biz/goethes-mefisto-plzen?adjust_creative=5hutJMpTIMEz7crE-Bac2Q&utm_campaign=yelp_api_v3&utm_medium=api_v3_business_search&utm_source=5hutJMpTIMEz7crE-Bac2Q",
    "image_url": "",
    "name": "Goethe's Mefisto",
    "alias": "goethes-mefisto-plzen",
    "main_category": "Nightlife",
    "sub_categories": "Nightlife, ",
    "rating": 4.5,
    "price": "$",
    "address": "Goethova   9/2",
    "city_from_postal": "Plzeň-jih",
    "city": "Plzen",
    "zip_code": "301 00",
    "country_code": "CZ",
    "state_code": "PL",
    "phone": "",
    "review_count": 2,
    "snippets": []
  },
  "459096": {
    "url": "https://www.yelp.com/biz/restaurace-u-salzmann%C5%AF-plze%C5%88-2?adjust_creative=5hutJMpTIMEz7crE-Bac2Q&utm_campaign=yelp_api_v3&utm_medium=api_v3_business_search&utm_source=5hutJMpTIMEz7crE-Bac2Q",
    "image_url": "https://s3-media1.fl.yelpcdn.com/bphoto/36fA1s2SbSIauJYwPnypYQ/o.jpg",
    "name": "Restaurace U Salzmannů",
    "alias": "restaurace-u-salzmannů-plzeň-2",
    "main_category": "Restaurants and Food",
    "sub_categories": "Breweries, Czech, Pubs, ",
    "rating": 4.0,
    "price": "$$",
    "address": "Pražská 90/8",
    "city_from_postal": "Plzeň-jih",
    "city": "Plzeň",
    "zip_code": "301 00",
    "country_code": "CZ",
    "state_code": "PL",
    "phone": "+420377235855",
    "review_count": 20,
    "snippets": []
  },
  "468885": {
    "url": "https://www.yelp.com/biz/paintball-chot%C4%9B%C5%A1ov-chot%C4%9B%C5%A1ov?adjust_creative=5hutJMpTIMEz7crE-Bac2Q&utm_campaign=yelp_api_v3&utm_medium=api_v3_business_search&utm_source=5hutJMpTIMEz7crE-Bac2Q",
    "image_url": "",
    "name": "Paintball Chotěšov",
    "alias": "paintball-chotěšov-chotěšov",
    "main_category": "Active Life",
    "sub_categories": "Paintball, ",
    "rating": 5.0,
    "price": null,
    "address": "U řeky 632",
    "city_from_postal": "Plzeň-jih",
    "city": "Chotěšov",
    "zip_code": "332 14",
    "country_code": "CZ",
    "state_code": "PL",
    "phone": "+420607553536",
    "review_count": 1,
    "snippets": []
  },
  "475274": {
    "url": "https://www.yelp.com/biz/i%C4%8Dko-akademick%C3%A9-centrum-plzen?adjust_creative=5hutJMpTIMEz7crE-Bac2Q&utm_campaign=yelp_api_v3&utm_medium=api_v3_business_search&utm_source=5hutJMpTIMEz7crE-Bac2Q",
    "image_url": "https://s3-media4.fl.yelpcdn.com/bphoto/wrODrrp8tXCYdo7GQ2KnyQ/o.jpg",
    "name": "Ičko - akademické centrum",
    "alias": "ičko-akademické-centrum-plzen",
    "main_category": "Nightlife",
    "sub_categories": "Bars, ",
    "rating": 3.0,
    "price": "$$",
    "address": "sady 5. května 2",
    "city_from_postal": "Plzeň-jih",
    "city": "Plzen",
    "zip_code": "301 00",
    "country_code": "CZ",
    "state_code": "PL",
    "phone": "",
    "review_count": 2,
    "snippets": []
  },
  "476869": {
    "url": "https://www.yelp.com/biz/divadlo-josefa-kajet%C3%A1na-tyla-plze%C5%88?adjust_creative=5hutJMpTIMEz7crE-Bac2Q&utm_campaign=yelp_api_v3&utm_medium=api_v3_business_search&utm_source=5hutJMpTIMEz7crE-Bac2Q",
    "image_url": "https://s3-media1.fl.yelpcdn.com/bphoto/TpMFpVl4hUdnBLhmvbmlGg/o.jpg",
    "name": "Divadlo Josefa Kajetána Tyla",
    "alias": "divadlo-josefa-kajetána-tyla-plzeň",
    "main_category": "Arts & Entertainment",
    "sub_categories": "Opera & Ballet, Music Venues, ",
    "rating": 2.0,
    "price": "$$",
    "address": "Smetanovy sady 1129/1",
    "city_from_postal": "Plzeň-jih",
    "city": "Plzeň",
    "zip_code": "301 00",
    "country_code": "CZ",
    "state_code": "PL",
    "phone": "+420377226743",
    "review_count": 1,
    "snippets": []
  },
  "502689": {
    "url": "https://www.yelp.com/biz/pizzeria-a-restaurant-mikul%C3%A1%C5%A1sk%C3%A1-plze%C5%88?adjust_creative=5hutJMpTIMEz7crE-Bac2Q&utm_campaign=yelp_api_v3&utm_medium=api_v3_business_search&utm_source=5hutJMpTIMEz7crE-Bac2Q",
    "image_url": "https://s3-media2.fl.yelpcdn.com/bphoto/49GG1y81LU99C0gCtcoEnA/o.jpg",
    "name": "Pizzeria & Restaurant Mikulášská",
    "alias": "pizzeria-a-restaurant-mikulášská-plzeň",
    "main_category": "Restaurants and Food",
    "sub_categories": "Pizza, Cafes, Wine Bars, ",
    "rating": 2.0,
    "price": "$",
    "address": "Mikulášské náměstí 522/19",
    "city_from_postal": "Plzeň-jih",
    "city": "Plzeň",
    "zip_code": "326 00",
    "country_code": "CZ",
    "state_code": "PL",
    "phone": "+420773045871",
    "review_count": 3,
    "snippets": []
  },
  "526256": {
    "url": "https://www.yelp.com/biz/cuba-liberta-plze%C5%88?adjust_creative=5hutJMpTIMEz7crE-Bac2Q&utm_campaign=yelp_api_v3&utm_medium=api_v3_business_search&utm_source=5hutJMpTIMEz7crE-Bac2Q",
    "image_url": "https://s3-media4.fl.yelpcdn.com/bphoto/ik55IhwbtoeuhQjYM2avBQ/o.jpg",
    "name": "Cuba Liberta",
    "alias": "cuba-liberta-plzeň",
    "main_category": "Nightlife",
    "sub_categories": "Cocktail Bars, Cuban, ",
    "rating": 3.0,
    "price": null,
    "address": "Prokopova 21",
    "city_from_postal": "Plzeň-jih",
    "city": "Plzeň",
    "zip_code": "301 00",
    "country_code": "CZ",
    "state_code": "PL",
    "phone": "",
    "review_count": 1,
    "snippets": []
  },
  "541852": {
    "url": "https://www.yelp.com/biz/buffalo-burger-bar-pilsen?adjust_creative=5hutJMpTIMEz7crE-Bac2Q&utm_campaign=yelp_api_v3&utm_medium=api_v3_business_search&utm_source=5hutJMpTIMEz7crE-Bac2Q",
    "image_url": "https://s3-media2.fl.yelpcdn.com/bphoto/-4eYkX9c-e91woj49OwOKQ/o.jpg",
    "name": "Buffalo Burger Bar",
    "alias": "buffalo-burger-bar-pilsen",
    "main_category": "Nightlife",
    "sub_categories": "Bars, Burgers, ",
    "rating": 5.0,
    "price": null,
    "address": "Dominikánská 11",
    "city_from_postal": "Plzeň-jih",
    "city": "Pilsen",
    "zip_code": "301 00",
    "country_code": "CZ",
    "state_code": "JC",
    "phone": "+420733124514",
    "review_count": 1,
    "snippets": []
  },
  "552019": {
    "url": "https://www.yelp.com/biz/kav%C3%A1rna-inkognito-plzen-3?adjust_creative=5hutJMpTIMEz7crE-Bac2Q&utm_campaign=yelp_api_v3&utm_medium=api_v3_business_search&utm_source=5hutJMpTIMEz7crE-Bac2Q",
    "image_url": "https://s3-media2.fl.yelpcdn.com/bphoto/NvuVsfwRy_kq0n7c-Bjv-Q/o.jpg",
    "name": "Kavárna INKOGNITO",
    "alias": "kavárna-inkognito-plzen-3",
    "main_category": "Restaurants and Food",
    "sub_categories": "Coffee & Tea, Art Galleries, Cafes, ",
    "rating": 3.5,
    "price": "$$",
    "address": "Husova 24",
    "city_from_postal": "Plzeň-jih",
    "city": "Plzen",
    "zip_code": "301 00",
    "country_code": "CZ",
    "state_code": "PL",
    "phone": "+420731886333",
    "review_count": 2,
    "snippets": []
  },
  "571296": {
    "url": "https://www.yelp.com/biz/pivovar-restaurant-modr%C3%A1-hv%C4%9Bzda-dob%C5%99any?adjust_creative=NOl6cNLLkrD4j74baZTyew&utm_campaign=yelp_api_v3&utm_medium=api_v3_business_search&utm_source=NOl6cNLLkrD4j74baZTyew",
    "image_url": "https://s3-media4.fl.yelpcdn.com/bphoto/-sieClIHG0MuXesjF1Jf9w/o.jpg",
    "name": "Pivovar - restaurant Modrá Hvězda",
    "alias": "pivovar-restaurant-modrá-hvězda-dobřany",
    "main_category": "Shopping",
    "sub_categories": "Shopping, Active Life, Breweries, Restaurants, ",
    "rating": 2.5,
    "price": "$",
    "address": "Náměstí T. G. M. 159",
    "city_from_postal": "Plzeň-jih",
    "city": "Dobřany",
    "zip_code": "334 41",
    "country_code": "CZ",
    "state_code": "PL",
    "phone": "+420377973770",
    "review_count": 4,
    "snippets": []
  },
  "574418": {
    "url": "https://www.yelp.com/biz/rock-n-wall-plze%C5%88?adjust_creative=5hutJMpTIMEz7crE-Bac2Q&utm_campaign=yelp_api_v3&utm_medium=api_v3_business_search&utm_source=5hutJMpTIMEz7crE-Bac2Q",
    "image_url": "",
    "name": "Rock 'n' Wall",
    "alias": "rock-n-wall-plzeň",
    "main_category": "Nightlife",
    "sub_categories": "Bars, Climbing, ",
    "rating": 4.0,
    "price": null,
    "address": "Sady 5.května 24",
    "city_from_postal": "Plzeň-jih",
    "city": "Plzeň",
    "zip_code": "301 00",
    "country_code": "CZ",
    "state_code": "PL",
    "phone": "+420602305222",
    "review_count": 1,
    "snippets": []
  },
  "610148": {
    "url": "https://www.yelp.com/biz/zapa-bar-plze%C5%88-2?adjust_creative=5hutJMpTIMEz7crE-Bac2Q&utm_campaign=yelp_api_v3&utm_medium=api_v3_business_search&utm_source=5hutJMpTIMEz7crE-Bac2Q",
    "image_url": "https://s3-media2.fl.yelpcdn.com/bphoto/L9KVl6jdKw4Rw0WKMBpZAw/o.jpg",
    "name": "Zapa Bar",
    "alias": "zapa-bar-plzeň-2",
    "main_category": "Nightlife",
    "sub_categories": "Cocktail Bars, ",
    "rating": 3.0,
    "price": "$$",
    "address": "Bedřicha Smetany 6",
    "city_from_postal": "Plzeň-jih",
    "city": "Plzeň",
    "zip_code": "301 00",
    "country_code": "CZ",
    "state_code": "PL",
    "phone": "+420377227427",
    "review_count": 1,
    "snippets": []
  },
  "627720": {
    "url": "https://www.yelp.com/biz/zoologick%C3%A1-a-botanick%C3%A1-zahrada-m%C4%9Bsta-plzn%C4%9B-plze%C5%88?adjust_creative=5hutJMpTIMEz7crE-Bac2Q&utm_campaign=yelp_api_v3&utm_medium=api_v3_business_search&utm_source=5hutJMpTIMEz7crE-Bac2Q",
    "image_url": "https://s3-media2.fl.yelpcdn.com/bphoto/s6NZgLCLGhsn3V4lb1AD2g/o.jpg",
    "name": "Zoologická a botanická zahrada města Plzně",
    "alias": "zoologická-a-botanická-zahrada-města-plzně-plzeň",
    "main_category": "Arts & Entertainment",
    "sub_categories": "Botanical Gardens, Zoos, ",
    "rating": 4.0,
    "price": null,
    "address": "Pod Vinicemi 928/9",
    "city_from_postal": "Plzeň-jih",
    "city": "Plzeň",
    "zip_code": "301 00",
    "country_code": "CZ",
    "state_code": "PL",
    "phone": "+420378038325",
    "review_count": 1,
    "snippets": []
  },
  "633849": {
    "url": "https://www.yelp.com/biz/potrefen%C3%A1-husa-plzen?adjust_creative=5hutJMpTIMEz7crE-Bac2Q&utm_campaign=yelp_api_v3&utm_medium=api_v3_business_search&utm_source=5hutJMpTIMEz7crE-Bac2Q",
    "image_url": "https://s3-media1.fl.yelpcdn.com/bphoto/Q-ywqNcpFpPKzAekG1IsjA/o.jpg",
    "name": "Potrefená Husa",
    "alias": "potrefená-husa-plzen",
    "main_category": "Nightlife",
    "sub_categories": "Bars, ",
    "rating": 5.0,
    "price": "$$",
    "address": "Martinská 1",
    "city_from_postal": "Plzeň-jih",
    "city": "Plzen",
    "zip_code": "301 00",
    "country_code": "CZ",
    "state_code": "PL",
    "phone": "+420377320832",
    "review_count": 4,
    "snippets": []
  }
}