{
  "20547": {
    "url": "https://www.yelp.com/biz/schlossgarten-kilchberg?adjust_creative=5hutJMpTIMEz7crE-Bac2Q&utm_campaign=yelp_api_v3&utm_medium=api_v3_business_search&utm_source=5hutJMpTIMEz7crE-Bac2Q",
    "image_url": "https://s3-media4.fl.yelpcdn.com/bphoto/9DNdVFQE4427-1dEqDncuA/o.jpg",
    "name": "Schlossgarten",
    "alias": "schlossgarten-kilchberg",
    "main_category": "Restaurants and Food",
    "sub_categories": "Italian, ",
    "rating": 2.5,
    "price": "$$$",
    "address": "Dorfstrasse 132",
    "city_from_postal": "Kilchberg (ZH)",
    "city": "Kilchberg",
    "zip_code": "8802",
    "country_code": "CH",
    "state_code": "ZH",
    "phone": "+41447155330",
    "review_count": 2,
    "snippets": []
  },
  "33949": {
    "url": "https://www.yelp.com/biz/ochsen-michael-kilchberg?adjust_creative=5hutJMpTIMEz7crE-Bac2Q&utm_campaign=yelp_api_v3&utm_medium=api_v3_business_search&utm_source=5hutJMpTIMEz7crE-Bac2Q",
    "image_url": "https://s3-media2.fl.yelpcdn.com/bphoto/osaAj6v-hBk2L6eHqTg9Og/o.jpg",
    "name": "Ochsen Michael",
    "alias": "ochsen-michael-kilchberg",
    "main_category": "Restaurants and Food",
    "sub_categories": "Italian, Pizza, Swiss Food, ",
    "rating": 2.0,
    "price": null,
    "address": "Bahnhofstrasse 15",
    "city_from_postal": "Kilchberg (ZH)",
    "city": "Kilchberg",
    "zip_code": "8802",
    "country_code": "CH",
    "state_code": "ZH",
    "phone": "+41447153015",
    "review_count": 1,
    "snippets": []
  },
  "112441": {
    "url": "https://www.yelp.com/biz/oberer-m%C3%B6nchhof-kilchberg?adjust_creative=5hutJMpTIMEz7crE-Bac2Q&utm_campaign=yelp_api_v3&utm_medium=api_v3_business_search&utm_source=5hutJMpTIMEz7crE-Bac2Q",
    "image_url": "https://s3-media2.fl.yelpcdn.com/bphoto/YJqTHxx8GI04AzYxpMxAgg/o.jpg",
    "name": "Oberer Mönchhof",
    "alias": "oberer-mönchhof-kilchberg",
    "main_category": "Restaurants and Food",
    "sub_categories": "Swiss Food, ",
    "rating": 3.5,
    "price": "$$$$",
    "address": "Alte Landstrasse 98",
    "city_from_postal": "Kilchberg (ZH)",
    "city": "Kilchberg",
    "zip_code": "8802",
    "country_code": "CH",
    "state_code": "ZH",
    "phone": "+41447154006",
    "review_count": 3,
    "snippets": []
  },
  "252506": {
    "url": "https://www.yelp.com/biz/lindt-factory-outlet-kilchberg?adjust_creative=5hutJMpTIMEz7crE-Bac2Q&utm_campaign=yelp_api_v3&utm_medium=api_v3_business_search&utm_source=5hutJMpTIMEz7crE-Bac2Q",
    "image_url": "https://s3-media4.fl.yelpcdn.com/bphoto/8pbeMGojIbbpbhpD2WyHUQ/o.jpg",
    "name": "Lindt Factory Outlet",
    "alias": "lindt-factory-outlet-kilchberg",
    "main_category": "Restaurants and Food",
    "sub_categories": "Chocolatiers & Shops, ",
    "rating": 4.0,
    "price": "$$",
    "address": "Pilgerweg 58",
    "city_from_postal": "Kilchberg (ZH)",
    "city": "Kilchberg",
    "zip_code": "8802",
    "country_code": "CH",
    "state_code": "ZH",
    "phone": "+41433770780",
    "review_count": 5,
    "snippets": []
  },
  "271470": {
    "url": "https://www.yelp.com/biz/villa-loca-kilchberg?adjust_creative=5hutJMpTIMEz7crE-Bac2Q&utm_campaign=yelp_api_v3&utm_medium=api_v3_business_search&utm_source=5hutJMpTIMEz7crE-Bac2Q",
    "image_url": "https://s3-media1.fl.yelpcdn.com/bphoto/lEG8IkGppVK1SzerW6xiuQ/o.jpg",
    "name": "Villa Loca",
    "alias": "villa-loca-kilchberg",
    "main_category": "Nightlife",
    "sub_categories": "Bars, Tex-Mex, Mexican, ",
    "rating": 5.0,
    "price": "$$",
    "address": "Seestrasse 30",
    "city_from_postal": "Kilchberg (ZH)",
    "city": "Kilchberg",
    "zip_code": "8802",
    "country_code": "CH",
    "state_code": "AG",
    "phone": "+41447154335",
    "review_count": 1,
    "snippets": []
  },
  "300876": {
    "url": "https://www.yelp.com/biz/b%C3%A4cker-k%C3%A4nzig-kilchberg?adjust_creative=5hutJMpTIMEz7crE-Bac2Q&utm_campaign=yelp_api_v3&utm_medium=api_v3_business_search&utm_source=5hutJMpTIMEz7crE-Bac2Q",
    "image_url": "https://s3-media2.fl.yelpcdn.com/bphoto/CX2cvi9uVsphgVqUFk7dGg/o.jpg",
    "name": "Bäcker Känzig",
    "alias": "bäcker-känzig-kilchberg",
    "main_category": "Restaurants and Food",
    "sub_categories": "Cafes, Bakeries, Patisserie/Cake Shop, ",
    "rating": 4.5,
    "price": null,
    "address": "Bahnhofstrasse 5",
    "city_from_postal": "Kilchberg (ZH)",
    "city": "Kilchberg",
    "zip_code": "8802",
    "country_code": "CH",
    "state_code": "ZH",
    "phone": "+41447154001",
    "review_count": 3,
    "snippets": []
  },
  "323685": {
    "url": "https://www.yelp.com/biz/restaurant-bar-m%C3%B6nchhof-kilchberg?adjust_creative=5hutJMpTIMEz7crE-Bac2Q&utm_campaign=yelp_api_v3&utm_medium=api_v3_business_search&utm_source=5hutJMpTIMEz7crE-Bac2Q",
    "image_url": "https://s3-media2.fl.yelpcdn.com/bphoto/mu-JskWtUqXKzg69DjjeLQ/o.jpg",
    "name": "Restaurant Bar Mönchhof",
    "alias": "restaurant-bar-mönchhof-kilchberg",
    "main_category": "Restaurants and Food",
    "sub_categories": "Beer, Wine & Spirits, Steakhouses, Tex-Mex, Mexican, ",
    "rating": 4.5,
    "price": "$$",
    "address": "Seestrasse 30",
    "city_from_postal": "Kilchberg (ZH)",
    "city": "Kilchberg",
    "zip_code": "8802",
    "country_code": "CH",
    "state_code": "ZH",
    "phone": "+41447154335",
    "review_count": 3,
    "snippets": []
  },
  "338795": {
    "url": "https://www.yelp.com/biz/sweet-und-sour-kilchberg?adjust_creative=5hutJMpTIMEz7crE-Bac2Q&utm_campaign=yelp_api_v3&utm_medium=api_v3_business_search&utm_source=5hutJMpTIMEz7crE-Bac2Q",
    "image_url": "https://s3-media1.fl.yelpcdn.com/bphoto/2zttLJSFZ5siYodxk9YQiQ/o.jpg",
    "name": "Sweet & Sour",
    "alias": "sweet-und-sour-kilchberg",
    "main_category": "Restaurants and Food",
    "sub_categories": "Asian Fusion, Thai, ",
    "rating": 1.0,
    "price": null,
    "address": "Seestrasse 30",
    "city_from_postal": "Kilchberg (ZH)",
    "city": "Kilchberg",
    "zip_code": "8802",
    "country_code": "CH",
    "state_code": "ZH",
    "phone": "+41446666868",
    "review_count": 1,
    "snippets": []
  },
  "374022": {
    "url": "https://www.yelp.com/biz/m%C3%B6nchhof-am-see-kilchberg-zh-2?adjust_creative=5hutJMpTIMEz7crE-Bac2Q&utm_campaign=yelp_api_v3&utm_medium=api_v3_business_search&utm_source=5hutJMpTIMEz7crE-Bac2Q",
    "image_url": "https://s3-media4.fl.yelpcdn.com/bphoto/8Eui7kCi4FLrHar0cCeucw/o.jpg",
    "name": "Mönchhof am See",
    "alias": "mönchhof-am-see-kilchberg-zh-2",
    "main_category": "Nightlife",
    "sub_categories": "Bars, Mediterranean, Barbeque, ",
    "rating": 3.0,
    "price": "$$$",
    "address": "Seestrasse 30",
    "city_from_postal": "Kilchberg (ZH)",
    "city": "Kilchberg ZH",
    "zip_code": "8802",
    "country_code": "CH",
    "state_code": "ZH",
    "phone": "+41447155009",
    "review_count": 7,
    "snippets": []
  },
  "437654": {
    "url": "https://www.yelp.com/biz/restaurant-chez-fritz-kilchberg?adjust_creative=5hutJMpTIMEz7crE-Bac2Q&utm_campaign=yelp_api_v3&utm_medium=api_v3_business_search&utm_source=5hutJMpTIMEz7crE-Bac2Q",
    "image_url": "https://s3-media3.fl.yelpcdn.com/bphoto/cIegELexajQ72Uji2-zE1w/o.jpg",
    "name": "Restaurant Chez Fritz",
    "alias": "restaurant-chez-fritz-kilchberg",
    "main_category": "Restaurants and Food",
    "sub_categories": "International, ",
    "rating": 4.5,
    "price": "$$$",
    "address": "Seestrasse 195b",
    "city_from_postal": "Kilchberg (ZH)",
    "city": "Kilchberg",
    "zip_code": "8802",
    "country_code": "CH",
    "state_code": "ZH",
    "phone": "+41447152515",
    "review_count": 10,
    "snippets": []
  },
  "510368": {
    "url": "https://www.yelp.com/biz/sushi-al-lago-kilchberg-zh?adjust_creative=5hutJMpTIMEz7crE-Bac2Q&utm_campaign=yelp_api_v3&utm_medium=api_v3_business_search&utm_source=5hutJMpTIMEz7crE-Bac2Q",
    "image_url": "",
    "name": "Sushi al Lago",
    "alias": "sushi-al-lago-kilchberg-zh",
    "main_category": "Restaurants and Food",
    "sub_categories": "Beauty & Spas, Japanese, ",
    "rating": 3.0,
    "price": null,
    "address": "Seestrasse 150",
    "city_from_postal": "Kilchberg (ZH)",
    "city": "Kilchberg ZH",
    "zip_code": "8802",
    "country_code": "CH",
    "state_code": "ZH",
    "phone": "+41447154066",
    "review_count": 1,
    "snippets": []
  },
  "670078": {
    "url": "https://www.yelp.com/biz/badi-beim-bootssteg-kilchberg-kilchberg?adjust_creative=5hutJMpTIMEz7crE-Bac2Q&utm_campaign=yelp_api_v3&utm_medium=api_v3_business_search&utm_source=5hutJMpTIMEz7crE-Bac2Q",
    "image_url": "",
    "name": "Badi beim Bootssteg Kilchberg",
    "alias": "badi-beim-bootssteg-kilchberg-kilchberg",
    "main_category": "Active Life",
    "sub_categories": "Local Flavor, Beaches, ",
    "rating": 4.0,
    "price": null,
    "address": "Seestrasse",
    "city_from_postal": "Kilchberg (ZH)",
    "city": "Kilchberg",
    "zip_code": "8802",
    "country_code": "CH",
    "state_code": "ZH",
    "phone": "",
    "review_count": 1,
    "snippets": []
  }
}